{"task_id": "95990924", "status": "ok", "reason": null, "config": {"epochs": 2000, "steps": 25, "lr": 0.001, "hidden": 32}, "best_loss": 0.021858, "pairs": [{"pair": 0, "input": [[0, 0, 0, 0, 0, 0, 0, 0, 0, 0], [0, 0, 0, 0, 0, 0, 0, 0, 0, 0], [0, 0, 5, 5, 0, 0, 0, 0, 0, 0], [0, 0, 5, 5, 0, 0, 0, 0, 0, 0], [0, 0, 0, 0, 0, 0, 0, 0, 0, 0], [0, 0, 0, 0, 0, 0, 0, 0, 0, 0], [0, 0, 0, 0, 0, 0, 5, 5, 0, 0], [0, 0, 0, 0, 0, 0, 5, 5, 0, 0], [0, 0, 0, 0, 0, 0, 0, 0, 0, 0], [0, 0, 0, 0, 0, 0, 0, 0, 0, 0]], "target": [[0, 0, 0, 0, 0, 0, 0, 0, 0, 0], [0, 1, 0, 0, 2, 0, 0, 0, 0, 0], [0, 0, 5, 5, 0, 0, 0, 0, 0, 0], [0, 0, 5, 5, 0, 0, 0, 0, 0, 0], [0, 3, 0, 0, 4, 0, 0, 0, 0, 0], [0, 0, 0, 0, 0, 1, 0, 0, 2, 0], [0, 0, 0, 0, 0, 0, 5, 5, 0, 0], [0, 0, 0, 0, 0, 0, 5, 5, 0, 0], [0, 0, 0, 0, 0, 3, 0, 0, 4, 0], [0, 0, 0, 0, 0, 0, 0, 0, 0, 0]], "steps": [[[0, 0, 0, 0, 0, 0, 0, 0, 0, 0], [0, 0, 0, 0, 0, 0, 0, 0, 0, 0], [0, 0, 5, 5, 0, 0, 0, 0, 0, 0], [0, 0, 5, 5, 0, 0, 0, 0, 0, 0], [0, 0, 0, 0, 0, 0, 0, 0, 0, 0], [0, 0, 0, 0, 0, 0, 0, 0, 0, 0], [0, 0, 0, 0, 0, 0, 5, 5, 0, 0], [0, 0, 0, 0, 0, 0, 5, 5, 0, 0], [0, 0, 0, 0, 0, 0, 0, 0, 0, 0], [0, 0, 0, 0, 0, 0, 0, 0, 0, 0]], [[0, 0, 0, 0, 0, 0, 0, 0, 0, 0], [0, 0, 0, 0, 0, 0, 0, 0, 0, 0], [0, 0, 5, 5, 0, 0, 0, 0, 0, 0], [0, 0, 5, 5, 0, 0, 0, 0, 0, 0], [0, 0, 0, 0, 0, 0, 0, 0, 0, 0], [0, 0, 0, 0, 0, 0, 0, 0, 0, 0], [0, 0, 0, 0, 0, 0, 5, 5, 0, 0], [0, 0, 0, 0, 0, 0, 5, 5, 0, 0], [0, 0, 0, 0, 0, 0, 0, 0, 0, 0], [0, 0, 0, 0, 0, 0, 0, 0, 0, 0]], [[0, 0, 0, 0, 0, 0, 0, 0, 0, 0], [0, 0, 0, 0, 0, 0, 0, 0, 0, 0], [0, 0, 5, 5, 0, 0, 0, 0, 0, 0], [0, 0, 5, 5, 0, 0, 0, 0, 0, 0], [0, 0, 0, 0, 0, 0, 0, 0, 0, 0], [0, 0, 0, 0, 0, 0, 0, 0, 0, 0], [0, 0, 0, 0, 0, 0, 5, 5, 0, 0], [0, 0, 0, 0, 0, 0, 5, 5, 0, 0], [0, 0, 0, 0, 0, 0, 0, 0, 0, 0], [0, 0, 0, 0, 0, 0, 0, 0, 0, 0]], [[0, 0, 0, 0, 0, 0, 0, 0, 0, 0], [0, 0, 0, 0, 0, 0, 0, 0, 0, 0], [0, 0, 5, 5, 0, 0, 0, 0, 0, 0], [0, 0, 5, 5, 0, 0, 0, 0, 0, 0], [0, 0, 0, 0, 4, 0, 0, 0, 0, 0], [0, 0, 0, 0, 0, 1, 0, 0, 0, 0], [0, 0, 0, 0, 0, 0, 5, 5, 0, 0], [0, 0, 0, 0, 0, 0, 5, 5, 0, 0], [0, 0, 0, 0, 0, 0, 0, 0, 4, 0], [0, 0, 0, 0, 0, 0, 0, 0, 0, 0]], [[0, 0, 0, 0, 0, 0, 0, 0, 0, 0], [0, 1, 0, 0, 2, 0, 0, 0, 0, 0], [0, 0, 5, 5, 0, 0, 0, 0, 0, 0], [0, 0, 5, 5, 0, 0, 0, 0, 0, 0], [0, 3, 0, 0, 4, 0, 0, 0, 0, 0], [0, 0, 0, 0, 0, 1, 0, 0, 0, 0], [0, 0, 0, 0, 0, 0, 5, 5, 0, 0], [0, 0, 0, 0, 0, 0, 5, 5, 0, 0], [0, 0, 0, 0, 0, 0, 0, 0, 4, 0], [0, 0, 0, 0, 0, 0, 0, 0, 0, 0]], [[0, 0, 0, 0, 0, 0, 0, 0, 0, 0], [0, 1, 0, 0, 2, 0, 0, 0, 0, 0], [0, 0, 5, 5, 0, 0, 0, 0, 0, 0], [0, 0, 5, 5, 0, 0, 0, 0, 0, 0], [0, 3, 0, 0, 4, 0, 0, 0, 0, 0], [0, 0, 0, 0, 0, 1, 0, 0, 2, 0], [0, 0, 0, 0, 0, 0, 5, 5, 0, 0], [0, 0, 0, 0, 0, 0, 5, 5, 0, 0], [0, 0, 0, 0, 0, 0, 0, 0, 4, 0], [0, 0, 0, 0, 0, 0, 0, 0, 0, 0]], [[0, 0, 0, 0, 0, 0, 0, 0, 0, 0], [0, 1, 0, 0, 2, 0, 0, 0, 0, 0], [0, 0, 5, 5, 0, 0, 0, 0, 0, 0], [0, 0, 5, 5, 0, 0, 0, 0, 0, 0], [0, 3, 0, 0, 4, 0, 0, 0, 0, 0], [0, 0, 0, 0, 0, 1, 0, 0, 2, 0], [0, 0, 0, 0, 0, 0, 5, 5, 0, 0], [0, 0, 0, 0, 0, 0, 5, 5, 0, 0], [0, 0, 0, 0, 0, 3, 0, 0, 4, 0], [0, 0, 0, 0, 0, 0, 0, 0, 0, 0]], [[0, 0, 0, 0, 0, 0, 0, 0, 0, 0], [0, 1, 0, 0, 2, 0, 0, 0, 0, 0], [0, 0, 5, 5, 0, 0, 0, 0, 0, 0], [0, 0, 5, 5, 0, 0, 0, 0, 0, 0], [0, 3, 0, 0, 4, 0, 0, 0, 0, 0], [0, 0, 0, 0, 0, 1, 0, 0, 2, 0], [0, 0, 0, 0, 0, 0, 5, 5, 0, 0], [0, 0, 0, 0, 0, 0, 5, 5, 0, 0], [0, 0, 0, 0, 0, 3, 0, 0, 4, 0], [0, 0, 0, 0, 0, 0, 0, 0, 0, 0]], [[0, 0, 0, 0, 0, 0, 0, 0, 0, 0], [0, 1, 0, 0, 2, 0, 0, 0, 0, 0], [0, 0, 5, 5, 0, 0, 0, 0, 0, 0], [0, 0, 5, 5, 0, 0, 0, 0, 0, 0], [0, 3, 0, 0, 4, 0, 0, 0, 0, 0], [0, 0, 0, 0, 0, 1, 0, 0, 2, 0], [0, 0, 0, 0, 0, 0, 5, 5, 0, 0], [0, 0, 0, 0, 0, 0, 5, 5, 0, 0], [0, 0, 0, 0, 0, 3, 0, 0, 4, 0], [0, 0, 0, 0, 0, 0, 0, 0, 0, 0]], [[0, 0, 0, 0, 0, 0, 0, 0, 0, 0], [0, 1, 0, 0, 2, 0, 0, 0, 0, 0], [0, 0, 5, 5, 0, 0, 0, 0, 0, 0], [0, 0, 5, 5, 0, 0, 0, 0, 0, 0], [0, 3, 0, 0, 4, 0, 0, 0, 0, 0], [0, 0, 0, 0, 0, 1, 0, 0, 2, 0], [0, 0, 0, 0, 0, 0, 5, 5, 0, 0], [0, 0, 0, 0, 0, 0, 5, 5, 0, 0], [0, 0, 0, 0, 0, 3, 0, 0, 4, 0], [0, 0, 0, 0, 0, 0, 0, 0, 0, 0]], [[0, 0, 0, 0, 0, 0, 0, 0, 0, 0], [0, 1, 0, 0, 2, 0, 0, 0, 0, 0], [0, 0, 5, 5, 0, 0, 0, 0, 0, 0], [0, 0, 5, 5, 0, 0, 0, 0, 0, 0], [0, 3, 0, 0, 4, 0, 0, 0, 0, 0], [0, 0, 0, 0, 0, 1, 0, 0, 2, 0], [0, 0, 0, 0, 0, 0, 5, 5, 0, 0], [0, 0, 0, 0, 0, 0, 5, 5, 0, 0], [0, 0, 0, 0, 0, 3, 0, 0, 4, 0], [0, 0, 0, 0, 0, 0, 0, 0, 0, 0]], [[0, 0, 0, 0, 0, 0, 0, 0, 0, 0], [0, 1, 0, 0, 2, 0, 0, 0, 0, 0], [0, 0, 5, 5, 0, 0, 0, 0, 0, 0], [0, 0, 5, 5, 0, 0, 0, 0, 0, 0], [0, 3, 0, 0, 4, 0, 0, 0, 0, 0], [0, 0, 0, 0, 0, 1, 0, 0, 2, 0], [0, 0, 0, 0, 0, 0, 5, 5, 0, 0], [0, 0, 0, 0, 0, 0, 5, 5, 0, 0], [0, 0, 0, 0, 0, 3, 0, 0, 4, 0], [0, 0, 0, 0, 0, 0, 0, 0, 0, 0]], [[0, 0, 0, 0, 0, 0, 0, 0, 0, 0], [0, 1, 0, 0, 2, 0, 0, 0, 0, 0], [0, 0, 5, 5, 0, 0, 0, 0, 0, 0], [0, 0, 5, 5, 0, 0, 0, 0, 0, 0], [0, 3, 0, 0, 4, 0, 0, 0, 0, 0], [0, 0, 0, 0, 0, 1, 0, 0, 2, 0], [0, 0, 0, 0, 0, 0, 5, 5, 0, 0], [0, 0, 0, 0, 0, 0, 5, 5, 0, 0], [0, 0, 0, 0, 0, 3, 0, 0, 4, 0], [0, 0, 0, 0, 0, 0, 0, 0, 0, 0]], [[0, 0, 0, 0, 0, 0, 0, 0, 0, 0], [0, 1, 0, 0, 2, 0, 0, 0, 0, 0], [0, 0, 5, 5, 0, 0, 0, 0, 0, 0], [0, 0, 5, 5, 0, 0, 0, 0, 0, 0], [0, 3, 0, 0, 4, 0, 0, 0, 0, 0], [0, 0, 0, 0, 0, 1, 0, 0, 2, 0], [0, 0, 0, 0, 0, 0, 5, 5, 0, 0], [0, 0, 0, 0, 0, 0, 5, 5, 0, 0], [0, 0, 0, 0, 0, 3, 0, 0, 4, 0], [0, 0, 0, 0, 0, 0, 0, 0, 0, 0]], [[0, 0, 0, 0, 0, 0, 0, 0, 0, 0], [0, 1, 0, 0, 2, 0, 0, 0, 0, 0], [0, 0, 5, 5, 0, 0, 0, 0, 0, 0], [0, 0, 5, 5, 0, 0, 0, 0, 0, 0], [0, 3, 0, 0, 4, 0, 0, 0, 0, 0], [0, 0, 0, 0, 0, 1, 0, 0, 2, 0], [0, 0, 0, 0, 0, 0, 5, 5, 0, 0], [0, 0, 0, 0, 0, 0, 5, 5, 0, 0], [0, 0, 0, 0, 0, 3, 0, 0, 4, 0], [0, 0, 0, 0, 0, 0, 0, 0, 0, 0]], [[0, 0, 0, 0, 0, 0, 0, 0, 0, 0], [0, 1, 0, 0, 2, 0, 0, 0, 0, 0], [0, 0, 5, 5, 0, 0, 0, 0, 0, 0], [0, 0, 5, 5, 0, 0, 0, 0, 0, 0], [0, 3, 0, 0, 4, 0, 0, 0, 0, 0], [0, 0, 0, 0, 0, 1, 0, 0, 2, 0], [0, 0, 0, 0, 0, 0, 5, 5, 0, 0], [0, 0, 0, 0, 0, 0, 5, 5, 0, 0], [0, 0, 0, 0, 0, 3, 0, 0, 4, 0], [0, 0, 0, 0, 0, 0, 0, 0, 0, 0]], [[0, 0, 0, 0, 0, 0, 0, 0, 0, 0], [0, 1, 0, 0, 2, 0, 0, 0, 0, 0], [0, 0, 5, 5, 0, 0, 0, 0, 0, 0], [0, 0, 5, 5, 0, 0, 0, 0, 0, 0], [0, 3, 0, 0, 4, 0, 0, 0, 0, 0], [0, 0, 0, 0, 0, 1, 0, 0, 2, 0], [0, 0, 0, 0, 0, 0, 5, 5, 0, 0], [0, 0, 0, 0, 0, 0, 5, 5, 0, 0], [0, 0, 0, 0, 0, 3, 0, 0, 4, 0], [0, 0, 0, 0, 0, 0, 0, 0, 0, 0]], [[0, 0, 0, 0, 0, 0, 0, 0, 0, 0], [0, 1, 0, 0, 2, 0, 0, 0, 0, 0], [0, 0, 5, 5, 0, 0, 0, 0, 0, 0], [0, 0, 5, 5, 0, 0, 0, 0, 0, 0], [0, 3, 0, 0, 4, 0, 0, 0, 0, 0], [0, 0, 0, 0, 0, 1, 0, 0, 2, 0], [0, 0, 0, 0, 0, 0, 5, 5, 0, 0], [0, 0, 0, 0, 0, 0, 5, 5, 0, 0], [0, 0, 0, 0, 0, 3, 0, 0, 4, 0], [0, 0, 0, 0, 0, 0, 0, 0, 0, 0]], [[0, 0, 0, 0, 0, 0, 0, 0, 0, 0], [0, 1, 0, 0, 2, 0, 0, 0, 0, 0], [0, 0, 5, 5, 0, 0, 0, 0, 0, 0], [0, 0, 5, 5, 0, 0, 0, 0, 0, 0], [0, 3, 0, 0, 4, 0, 0, 0, 0, 0], [0, 0, 0, 0, 0, 1, 0, 0, 2, 0], [0, 0, 0, 0, 0, 0, 5, 5, 0, 0], [0, 0, 0, 0, 0, 0, 5, 5, 0, 0], [0, 0, 0, 0, 0, 3, 0, 0, 4, 0], [0, 0, 0, 0, 0, 0, 0, 0, 0, 0]], [[0, 0, 0, 0, 0, 0, 0, 0, 0, 0], [0, 1, 0, 0, 2, 0, 0, 0, 0, 0], [0, 0, 5, 5, 0, 0, 0, 0, 0, 0], [0, 0, 5, 5, 0, 0, 0, 0, 0, 0], [0, 3, 0, 0, 4, 0, 0, 0, 0, 0], [0, 0, 0, 0, 0, 1, 0, 0, 2, 0], [0, 0, 0, 0, 0, 0, 5, 5, 0, 0], [0, 0, 0, 0, 0, 0, 5, 5, 0, 0], [0, 0, 0, 0, 0, 3, 0, 0, 4, 0], [0, 0, 0, 0, 0, 0, 0, 0, 0, 0]], [[0, 0, 0, 0, 0, 0, 0, 0, 0, 0], [0, 1, 0, 0, 2, 0, 0, 0, 0, 0], [0, 0, 5, 5, 0, 0, 0, 0, 0, 0], [0, 0, 5, 5, 0, 0, 0, 0, 0, 0], [0, 3, 0, 0, 4, 0, 0, 0, 0, 0], [0, 0, 0, 0, 0, 1, 0, 0, 2, 0], [0, 0, 0, 0, 0, 0, 5, 5, 0, 0], [0, 0, 0, 0, 0, 0, 5, 5, 0, 0], [0, 0, 0, 0, 0, 3, 0, 0, 4, 0], [0, 0, 0, 0, 0, 0, 0, 0, 0, 0]], [[0, 0, 0, 0, 0, 0, 0, 0, 0, 0], [0, 1, 0, 0, 2, 0, 0, 0, 0, 0], [0, 0, 5, 5, 0, 0, 0, 0, 0, 0], [0, 0, 5, 5, 0, 0, 0, 0, 0, 0], [0, 3, 0, 0, 4, 0, 0, 0, 0, 0], [0, 0, 0, 0, 0, 1, 0, 0, 2, 0], [0, 0, 0, 0, 0, 0, 5, 5, 0, 0], [0, 0, 0, 0, 0, 0, 5, 5, 0, 0], [0, 0, 0, 0, 0, 3, 0, 0, 4, 0], [0, 0, 0, 0, 0, 0, 0, 0, 0, 0]], [[0, 0, 0, 0, 0, 0, 0, 0, 0, 0], [0, 1, 0, 0, 2, 0, 0, 0, 0, 0], [0, 0, 5, 5, 0, 0, 0, 0, 0, 0], [0, 0, 5, 5, 0, 0, 0, 0, 0, 0], [0, 3, 0, 0, 4, 0, 0, 0, 0, 0], [0, 0, 0, 0, 0, 1, 0, 0, 2, 0], [0, 0, 0, 0, 0, 0, 5, 5, 0, 0], [0, 0, 0, 0, 0, 0, 5, 5, 0, 0], [0, 0, 0, 0, 0, 3, 0, 0, 4, 0], [0, 0, 0, 0, 0, 0, 0, 0, 0, 0]], [[0, 0, 0, 0, 0, 0, 0, 0, 0, 0], [0, 1, 0, 0, 2, 0, 0, 0, 0, 0], [0, 0, 5, 5, 0, 0, 0, 0, 0, 0], [0, 0, 5, 5, 0, 0, 0, 0, 0, 0], [0, 3, 0, 0, 4, 0, 0, 0, 0, 0], [0, 0, 0, 0, 0, 1, 0, 0, 2, 0], [0, 0, 0, 0, 0, 0, 5, 5, 0, 0], [0, 0, 0, 0, 0, 0, 5, 5, 0, 0], [0, 0, 0, 0, 0, 3, 0, 0, 4, 0], [0, 0, 0, 0, 0, 0, 0, 0, 0, 0]], [[0, 0, 0, 0, 0, 0, 0, 0, 0, 0], [0, 1, 0, 0, 2, 0, 0, 0, 0, 0], [0, 0, 5, 5, 0, 0, 0, 0, 0, 0], [0, 0, 5, 5, 0, 0, 0, 0, 0, 0], [0, 3, 0, 0, 4, 0, 0, 0, 0, 0], [0, 0, 0, 0, 0, 1, 0, 0, 2, 0], [0, 0, 0, 0, 0, 0, 5, 5, 0, 0], [0, 0, 0, 0, 0, 0, 5, 5, 0, 0], [0, 0, 0, 0, 0, 3, 0, 0, 4, 0], [0, 0, 0, 0, 0, 0, 0, 0, 0, 0]], [[0, 0, 0, 0, 0, 0, 0, 0, 0, 0], [0, 1, 0, 0, 2, 0, 0, 0, 0, 0], [0, 0, 5, 5, 0, 0, 0, 0, 0, 0], [0, 0, 5, 5, 0, 0, 0, 0, 0, 0], [0, 3, 0, 0, 4, 0, 0, 0, 0, 0], [0, 0, 0, 0, 0, 1, 0, 0, 2, 0], [0, 0, 0, 0, 0, 0, 5, 5, 0, 0], [0, 0, 0, 0, 0, 0, 5, 5, 0, 0], [0, 0, 0, 0, 0, 3, 0, 0, 4, 0], [0, 0, 0, 0, 0, 0, 0, 0, 0, 0]]], "accs": [92.0, 92.0, 92.0, 95.0, 98.0, 99.0, 100.0, 100.0, 100.0, 100.0, 100.0, 100.0, 100.0, 100.0, 100.0, 100.0, 100.0, 100.0, 100.0, 100.0, 100.0, 100.0, 100.0, 100.0, 100.0, 100.0], "exact": true}, {"pair": 1, "input": [[0, 0, 0, 0, 0, 0, 0, 0, 0, 0], [0, 0, 0, 0, 0, 0, 0, 0, 0, 0], [0, 0, 0, 0, 0, 0, 0, 0, 0, 0], [0, 0, 0, 0, 5, 5, 0, 0, 0, 0], [0, 0, 0, 0, 5, 5, 0, 0, 0, 0], [0, 0, 0, 0, 0, 0, 0, 0, 0, 0], [0, 0, 0, 0, 0, 0, 0, 0, 0, 0], [0, 0, 0, 0, 0, 0, 0, 0, 0, 0], [0, 0, 0, 0, 0, 0, 0, 0, 0, 0], [0, 0, 0, 0, 0, 0, 0, 0, 0, 0]], "target": [[0, 0, 0, 0, 0, 0, 0, 0, 0, 0], [0, 0, 0, 0, 0, 0, 0, 0, 0, 0], [0, 0, 0, 1, 0, 0, 2, 0, 0, 0], [0, 0, 0, 0, 5, 5, 0, 0, 0, 0], [0, 0, 0, 0, 5, 5, 0, 0, 0, 0], [0, 0, 0, 3, 0, 0, 4, 0, 0, 0], [0, 0, 0, 0, 0, 0, 0, 0, 0, 0], [0, 0, 0, 0, 0, 0, 0, 0, 0, 0], [0, 0, 0, 0, 0, 0, 0, 0, 0, 0], [0, 0, 0, 0, 0, 0, 0, 0, 0, 0]], "steps": [[[0, 0, 0, 0, 0, 0, 0, 0, 0, 0], [0, 0, 0, 0, 0, 0, 0, 0, 0, 0], [0, 0, 0, 0, 0, 0, 0, 0, 0, 0], [0, 0, 0, 0, 5, 5, 0, 0, 0, 0], [0, 0, 0, 0, 5, 5, 0, 0, 0, 0], [0, 0, 0, 0, 0, 0, 0, 0, 0, 0], [0, 0, 0, 0, 0, 0, 0, 0, 0, 0], [0, 0, 0, 0, 0, 0, 0, 0, 0, 0], [0, 0, 0, 0, 0, 0, 0, 0, 0, 0], [0, 0, 0, 0, 0, 0, 0, 0, 0, 0]], [[0, 0, 0, 0, 0, 0, 0, 0, 0, 0], [0, 0, 0, 0, 0, 0, 0, 0, 0, 0], [0, 0, 0, 0, 0, 0, 0, 0, 0, 0], [0, 0, 0, 0, 5, 5, 0, 0, 0, 0], [0, 0, 0, 0, 5, 5, 0, 0, 0, 0], [0, 0, 0, 0, 0, 0, 0, 0, 0, 0], [0, 0, 0, 0, 0, 0, 0, 0, 0, 0], [0, 0, 0, 0, 0, 0, 0, 0, 0, 0], [0, 0, 0, 0, 0, 0, 0, 0, 0, 0], [0, 0, 0, 0, 0, 0, 0, 0, 0, 0]], [[0, 0, 0, 0, 0, 0, 0, 0, 0, 0], [0, 0, 0, 0, 0, 0, 0, 0, 0, 0], [0, 0, 0, 0, 0, 0, 0, 0, 0, 0], [0, 0, 0, 0, 5, 5, 0, 0, 0, 0], [0, 0, 0, 0, 5, 5, 0, 0, 0, 0], [0, 0, 0, 0, 0, 0, 0, 0, 0, 0], [0, 0, 0, 0, 0, 0, 0, 0, 0, 0], [0, 0, 0, 0, 0, 0, 0, 0, 0, 0], [0, 0, 0, 0, 0, 0, 0, 0, 0, 0], [0, 0, 0, 0, 0, 0, 0, 0, 0, 0]], [[0, 0, 0, 0, 0, 0, 0, 0, 0, 0], [0, 0, 0, 0, 0, 0, 0, 0, 0, 0], [0, 0, 0, 0, 0, 0, 0, 0, 0, 0], [0, 0, 0, 0, 5, 5, 0, 0, 0, 0], [0, 0, 0, 0, 5, 5, 0, 0, 0, 0], [0, 0, 0, 0, 0, 0, 0, 0, 0, 0], [0, 0, 0, 0, 0, 0, 0, 0, 0, 0], [0, 0, 0, 0, 0, 0, 0, 0, 0, 0], [0, 0, 0, 0, 0, 0, 0, 0, 0, 0], [0, 0, 0, 0, 0, 0, 0, 0, 0, 0]], [[0, 0, 0, 0, 0, 0, 0, 0, 0, 0], [0, 0, 0, 0, 0, 0, 0, 0, 0, 0], [0, 0, 0, 1, 0, 0, 2, 0, 0, 0], [0, 0, 0, 0, 5, 5, 0, 0, 0, 0], [0, 0, 0, 0, 5, 5, 0, 0, 0, 0], [0, 0, 0, 0, 0, 0, 0, 0, 0, 0], [0, 0, 0, 0, 0, 0, 0, 0, 0, 0], [0, 0, 0, 0, 0, 0, 0, 0, 0, 0], [0, 0, 0, 0, 0, 0, 0, 0, 0, 0], [0, 0, 0, 0, 0, 0, 0, 0, 0, 0]], [[0, 0, 0, 0, 0, 0, 0, 0, 0, 0], [0, 0, 0, 0, 0, 0, 0, 0, 0, 0], [0, 0, 0, 1, 0, 0, 2, 0, 0, 0], [0, 0, 0, 0, 5, 5, 0, 0, 0, 0], [0, 0, 0, 0, 5, 5, 0, 0, 0, 0], [0, 0, 0, 0, 0, 0, 4, 0, 0, 0], [0, 0, 0, 0, 0, 0, 0, 0, 0, 0], [0, 0, 0, 0, 0, 0, 0, 0, 0, 0], [0, 0, 0, 0, 0, 0, 0, 0, 0, 0], [0, 0, 0, 0, 0, 0, 0, 0, 0, 0]], [[0, 0, 0, 0, 0, 0, 0, 0, 0, 0], [0, 0, 0, 0, 0, 0, 0, 0, 0, 0], [0, 0, 0, 1, 0, 0, 2, 0, 0, 0], [0, 0, 0, 0, 5, 5, 0, 0, 0, 0], [0, 0, 0, 0, 5, 5, 0, 0, 0, 0], [0, 0, 0, 0, 0, 0, 4, 0, 0, 0], [0, 0, 0, 0, 0, 0, 0, 0, 0, 0], [0, 0, 0, 0, 0, 0, 0, 0, 0, 0], [0, 0, 0, 0, 0, 0, 0, 0, 0, 0], [0, 0, 0, 0, 0, 0, 0, 0, 0, 0]], [[0, 0, 0, 0, 0, 0, 0, 0, 0, 0], [0, 0, 0, 0, 0, 0, 0, 0, 0, 0], [0, 0, 0, 1, 0, 0, 2, 0, 0, 0], [0, 0, 0, 0, 5, 5, 0, 0, 0, 0], [0, 0, 0, 0, 5, 5, 0, 0, 0, 0], [0, 0, 0, 0, 0, 0, 4, 0, 0, 0], [0, 0, 0, 0, 0, 0, 0, 0, 0, 0], [0, 0, 0, 0, 0, 0, 0, 0, 0, 0], [0, 0, 0, 0, 0, 0, 0, 0, 0, 0], [0, 0, 0, 0, 0, 0, 0, 0, 0, 0]], [[0, 0, 0, 0, 0, 0, 0, 0, 0, 0], [0, 0, 0, 0, 0, 0, 0, 0, 0, 0], [0, 0, 0, 1, 0, 0, 2, 0, 0, 0], [0, 0, 0, 0, 5, 5, 0, 0, 0, 0], [0, 0, 0, 0, 5, 5, 0, 0, 0, 0], [0, 0, 0, 3, 0, 0, 4, 0, 0, 0], [0, 0, 0, 0, 0, 0, 0, 0, 0, 0], [0, 0, 0, 0, 0, 0, 0, 0, 0, 0], [0, 0, 0, 0, 0, 0, 0, 0, 0, 0], [0, 0, 0, 0, 0, 0, 0, 0, 0, 0]], [[0, 0, 0, 0, 0, 0, 0, 0, 0, 0], [0, 0, 0, 0, 0, 0, 0, 0, 0, 0], [0, 0, 0, 1, 0, 0, 2, 0, 0, 0], [0, 0, 0, 0, 5, 5, 0, 0, 0, 0], [0, 0, 0, 0, 5, 5, 0, 0, 0, 0], [0, 0, 0, 3, 0, 0, 4, 0, 0, 0], [0, 0, 0, 0, 0, 0, 0, 0, 0, 0], [0, 0, 0, 0, 0, 0, 0, 0, 0, 0], [0, 0, 0, 0, 0, 0, 0, 0, 0, 0], [0, 0, 0, 0, 0, 0, 0, 0, 0, 0]], [[0, 0, 0, 0, 0, 0, 0, 0, 0, 0], [0, 0, 0, 0, 0, 0, 0, 0, 0, 0], [0, 0, 0, 1, 0, 0, 2, 0, 0, 0], [0, 0, 0, 0, 5, 5, 0, 0, 0, 0], [0, 0, 0, 0, 5, 5, 0, 0, 0, 0], [0, 0, 0, 3, 0, 0, 4, 0, 0, 0], [0, 0, 0, 0, 0, 0, 0, 0, 0, 0], [0, 0, 0, 0, 0, 0, 0, 0, 0, 0], [0, 0, 0, 0, 0, 0, 0, 0, 0, 0], [0, 0, 0, 0, 0, 0, 0, 0, 0, 0]], [[0, 0, 0, 0, 0, 0, 0, 0, 0, 0], [0, 0, 0, 0, 0, 0, 0, 0, 0, 0], [0, 0, 0, 1, 0, 0, 2, 0, 0, 0], [0, 0, 0, 0, 5, 5, 0, 0, 0, 0], [0, 0, 0, 0, 5, 5, 0, 0, 0, 0], [0, 0, 0, 3, 0, 0, 4, 0, 0, 0], [0, 0, 0, 0, 0, 0, 0, 0, 0, 0], [0, 0, 0, 0, 0, 0, 0, 0, 0, 0], [0, 0, 0, 0, 0, 0, 0, 0, 0, 0], [0, 0, 0, 0, 0, 0, 0, 0, 0, 0]], [[0, 0, 0, 0, 0, 0, 0, 0, 0, 0], [0, 0, 0, 0, 0, 0, 0, 0, 0, 0], [0, 0, 0, 1, 0, 0, 2, 0, 0, 0], [0, 0, 0, 0, 5, 5, 0, 0, 0, 0], [0, 0, 0, 0, 5, 5, 0, 0, 0, 0], [0, 0, 0, 3, 0, 0, 4, 0, 0, 0], [0, 0, 0, 0, 0, 0, 0, 0, 0, 0], [0, 0, 0, 0, 0, 0, 0, 0, 0, 0], [0, 0, 0, 0, 0, 0, 0, 0, 0, 0], [0, 0, 0, 0, 0, 0, 0, 0, 0, 0]], [[0, 0, 0, 0, 0, 0, 0, 0, 0, 0], [0, 0, 0, 0, 0, 0, 0, 0, 0, 0], [0, 0, 0, 1, 0, 0, 2, 0, 0, 0], [0, 0, 0, 0, 5, 5, 0, 0, 0, 0], [0, 0, 0, 0, 5, 5, 0, 0, 0, 0], [0, 0, 0, 3, 0, 0, 4, 0, 0, 0], [0, 0, 0, 0, 0, 0, 0, 0, 0, 0], [0, 0, 0, 0, 0, 0, 0, 0, 0, 0], [0, 0, 0, 0, 0, 0, 0, 0, 0, 0], [0, 0, 0, 0, 0, 0, 0, 0, 0, 0]], [[0, 0, 0, 0, 0, 0, 0, 0, 0, 0], [0, 0, 0, 0, 0, 0, 0, 0, 0, 0], [0, 0, 0, 1, 0, 0, 2, 0, 0, 0], [0, 0, 0, 0, 5, 5, 0, 0, 0, 0], [0, 0, 0, 0, 5, 5, 0, 0, 0, 0], [0, 0, 0, 3, 0, 0, 4, 0, 0, 0], [0, 0, 0, 0, 0, 0, 0, 0, 0, 0], [0, 0, 0, 0, 0, 0, 0, 0, 0, 0], [0, 0, 0, 0, 0, 0, 0, 0, 0, 0], [0, 0, 0, 0, 0, 0, 0, 0, 0, 0]], [[0, 0, 0, 0, 0, 0, 0, 0, 0, 0], [0, 0, 0, 0, 0, 0, 0, 0, 0, 0], [0, 0, 0, 1, 0, 0, 2, 0, 0, 0], [0, 0, 0, 0, 5, 5, 0, 0, 0, 0], [0, 0, 0, 0, 5, 5, 0, 0, 0, 0], [0, 0, 0, 3, 0, 0, 4, 0, 0, 0], [0, 0, 0, 0, 0, 0, 0, 0, 0, 0], [0, 0, 0, 0, 0, 0, 0, 0, 0, 0], [0, 0, 0, 0, 0, 0, 0, 0, 0, 0], [0, 0, 0, 0, 0, 0, 0, 0, 0, 0]], [[0, 0, 0, 0, 0, 0, 0, 0, 0, 0], [0, 0, 0, 0, 0, 0, 0, 0, 0, 0], [0, 0, 0, 1, 0, 0, 2, 0, 0, 0], [0, 0, 0, 0, 5, 5, 0, 0, 0, 0], [0, 0, 0, 0, 5, 5, 0, 0, 0, 0], [0, 0, 0, 3, 0, 0, 4, 0, 0, 0], [0, 0, 0, 0, 0, 0, 0, 0, 0, 0], [0, 0, 0, 0, 0, 0, 0, 0, 0, 0], [0, 0, 0, 0, 0, 0, 0, 0, 0, 0], [0, 0, 0, 0, 0, 0, 0, 0, 0, 0]], [[0, 0, 0, 0, 0, 0, 0, 0, 0, 0], [0, 0, 0, 0, 0, 0, 0, 0, 0, 0], [0, 0, 0, 1, 0, 0, 2, 0, 0, 0], [0, 0, 0, 0, 5, 5, 0, 0, 0, 0], [0, 0, 0, 0, 5, 5, 0, 0, 0, 0], [0, 0, 0, 3, 0, 0, 4, 0, 0, 0], [0, 0, 0, 0, 0, 0, 0, 0, 0, 0], [0, 0, 0, 0, 0, 0, 0, 0, 0, 0], [0, 0, 0, 0, 0, 0, 0, 0, 0, 0], [0, 0, 0, 0, 0, 0, 0, 0, 0, 0]], [[0, 0, 0, 0, 0, 0, 0, 0, 0, 0], [0, 0, 0, 0, 0, 0, 0, 0, 0, 0], [0, 0, 0, 1, 0, 0, 2, 0, 0, 0], [0, 0, 0, 0, 5, 5, 0, 0, 0, 0], [0, 0, 0, 0, 5, 5, 0, 0, 0, 0], [0, 0, 0, 3, 0, 0, 4, 0, 0, 0], [0, 0, 0, 0, 0, 0, 0, 0, 0, 0], [0, 0, 0, 0, 0, 0, 0, 0, 0, 0], [0, 0, 0, 0, 0, 0, 0, 0, 0, 0], [0, 0, 0, 0, 0, 0, 0, 0, 0, 0]], [[0, 0, 0, 0, 0, 0, 0, 0, 0, 0], [0, 0, 0, 0, 0, 0, 0, 0, 0, 0], [0, 0, 0, 1, 0, 0, 2, 0, 0, 0], [0, 0, 0, 0, 5, 5, 0, 0, 0, 0], [0, 0, 0, 0, 5, 5, 0, 0, 0, 0], [0, 0, 0, 3, 0, 0, 4, 0, 0, 0], [0, 0, 0, 0, 0, 0, 0, 0, 0, 0], [0, 0, 0, 0, 0, 0, 0, 0, 0, 0], [0, 0, 0, 0, 0, 0, 0, 0, 0, 0], [0, 0, 0, 0, 0, 0, 0, 0, 0, 0]], [[0, 0, 0, 0, 0, 0, 0, 0, 0, 0], [0, 0, 0, 0, 0, 0, 0, 0, 0, 0], [0, 0, 0, 1, 0, 0, 2, 0, 0, 0], [0, 0, 0, 0, 5, 5, 0, 0, 0, 0], [0, 0, 0, 0, 5, 5, 0, 0, 0, 0], [0, 0, 0, 3, 0, 0, 4, 0, 0, 0], [0, 0, 0, 0, 0, 0, 0, 0, 0, 0], [0, 0, 0, 0, 0, 0, 0, 0, 0, 0], [0, 0, 0, 0, 0, 0, 0, 0, 0, 0], [0, 0, 0, 0, 0, 0, 0, 0, 0, 0]], [[0, 0, 0, 0, 0, 0, 0, 0, 0, 0], [0, 0, 0, 0, 0, 0, 0, 0, 0, 0], [0, 0, 0, 1, 0, 0, 2, 0, 0, 0], [0, 0, 0, 0, 5, 5, 0, 0, 0, 0], [0, 0, 0, 0, 5, 5, 0, 0, 0, 0], [0, 0, 0, 3, 0, 0, 4, 0, 0, 0], [0, 0, 0, 0, 0, 0, 0, 0, 0, 0], [0, 0, 0, 0, 0, 0, 0, 0, 0, 0], [0, 0, 0, 0, 0, 0, 0, 0, 0, 0], [0, 0, 0, 0, 0, 0, 0, 0, 0, 0]], [[0, 0, 0, 0, 0, 0, 0, 0, 0, 0], [0, 0, 0, 0, 0, 0, 0, 0, 0, 0], [0, 0, 0, 1, 0, 0, 2, 0, 0, 0], [0, 0, 0, 0, 5, 5, 0, 0, 0, 0], [0, 0, 0, 0, 5, 5, 0, 0, 0, 0], [0, 0, 0, 3, 0, 0, 4, 0, 0, 0], [0, 0, 0, 0, 0, 0, 0, 0, 0, 0], [0, 0, 0, 0, 0, 0, 0, 0, 0, 0], [0, 0, 0, 0, 0, 0, 0, 0, 0, 0], [0, 0, 0, 0, 0, 0, 0, 0, 0, 0]], [[0, 0, 0, 0, 0, 0, 0, 0, 0, 0], [0, 0, 0, 0, 0, 0, 0, 0, 0, 0], [0, 0, 0, 1, 0, 0, 2, 0, 0, 0], [0, 0, 0, 0, 5, 5, 0, 0, 0, 0], [0, 0, 0, 0, 5, 5, 0, 0, 0, 0], [0, 0, 0, 3, 0, 0, 4, 0, 0, 0], [0, 0, 0, 0, 0, 0, 0, 0, 0, 0], [0, 0, 0, 0, 0, 0, 0, 0, 0, 0], [0, 0, 0, 0, 0, 0, 0, 0, 0, 0], [0, 0, 0, 0, 0, 0, 0, 0, 0, 0]], [[0, 0, 0, 0, 0, 0, 0, 0, 0, 0], [0, 0, 0, 0, 0, 0, 0, 0, 0, 0], [0, 0, 0, 1, 0, 0, 2, 0, 0, 0], [0, 0, 0, 0, 5, 5, 0, 0, 0, 0], [0, 0, 0, 0, 5, 5, 0, 0, 0, 0], [0, 0, 0, 3, 0, 0, 4, 0, 0, 0], [0, 0, 0, 0, 0, 0, 0, 0, 0, 0], [0, 0, 0, 0, 0, 0, 0, 0, 0, 0], [0, 0, 0, 0, 0, 0, 0, 0, 0, 0], [0, 0, 0, 0, 0, 0, 0, 0, 0, 0]], [[0, 0, 0, 0, 0, 0, 0, 0, 0, 0], [0, 0, 0, 0, 0, 0, 0, 0, 0, 0], [0, 0, 0, 1, 0, 0, 2, 0, 0, 0], [0, 0, 0, 0, 5, 5, 0, 0, 0, 0], [0, 0, 0, 0, 5, 5, 0, 0, 0, 0], [0, 0, 0, 3, 0, 0, 4, 0, 0, 0], [0, 0, 0, 0, 0, 0, 0, 0, 0, 0], [0, 0, 0, 0, 0, 0, 0, 0, 0, 0], [0, 0, 0, 0, 0, 0, 0, 0, 0, 0], [0, 0, 0, 0, 0, 0, 0, 0, 0, 0]]], "accs": [96.0, 96.0, 96.0, 96.0, 98.0, 99.0, 99.0, 99.0, 100.0, 100.0, 100.0, 100.0, 100.0, 100.0, 100.0, 100.0, 100.0, 100.0, 100.0, 100.0, 100.0, 100.0, 100.0, 100.0, 100.0, 100.0], "exact": true}, {"pair": 2, "input": [[0, 0, 0, 0, 0, 0, 0, 0, 0, 0, 0, 0, 0, 0, 0], [0, 0, 0, 0, 0, 0, 0, 0, 0, 0, 0, 0, 0, 0, 0], [0, 0, 0, 5, 5, 0, 0, 0, 0, 0, 0, 0, 0, 0, 0], [0, 0, 0, 5, 5, 0, 0, 0, 0, 0, 0, 0, 0, 0, 0], [0, 0, 0, 0, 0, 0, 0, 0, 5, 5, 0, 0, 0, 0, 0], [0, 0, 0, 0, 0, 0, 0, 0, 5, 5, 0, 0, 0, 0, 0], [0, 0, 0, 0, 0, 0, 0, 0, 0, 0, 0, 0, 0, 0, 0], [0, 0, 0, 0, 0, 0, 0, 0, 0, 0, 0, 0, 0, 0, 0], [0, 0, 0, 0, 5, 5, 0, 0, 0, 0, 0, 0, 0, 0, 0], [0, 0, 0, 0, 5, 5, 0, 0, 0, 0, 0, 0, 0, 0, 0], [0, 0, 0, 0, 0, 0, 0, 0, 0, 0, 0, 0, 0, 0, 0], [0, 0, 0, 0, 0, 0, 0, 0, 0, 5, 5, 0, 0, 0, 0], [0, 0, 0, 0, 0, 0, 0, 0, 0, 5, 5, 0, 0, 0, 0], [0, 0, 0, 0, 0, 0, 0, 0, 0, 0, 0, 0, 0, 0, 0], [0, 0, 0, 0, 0, 0, 0, 0, 0, 0, 0, 0, 0, 0, 0]], "target": [[0, 0, 0, 0, 0, 0, 0, 0, 0, 0, 0, 0, 0, 0, 0], [0, 0, 1, 0, 0, 2, 0, 0, 0, 0, 0, 0, 0, 0, 0], [0, 0, 0, 5, 5, 0, 0, 0, 0, 0, 0, 0, 0, 0, 0], [0, 0, 0, 5, 5, 0, 0, 1, 0, 0, 2, 0, 0, 0, 0], [0, 0, 3, 0, 0, 4, 0, 0, 5, 5, 0, 0, 0, 0, 0], [0, 0, 0, 0, 0, 0, 0, 0, 5, 5, 0, 0, 0, 0, 0], [0, 0, 0, 0, 0, 0, 0, 3, 0, 0, 4, 0, 0, 0, 0], [0, 0, 0, 1, 0, 0, 2, 0, 0, 0, 0, 0, 0, 0, 0], [0, 0, 0, 0, 5, 5, 0, 0, 0, 0, 0, 0, 0, 0, 0], [0, 0, 0, 0, 5, 5, 0, 0, 0, 0, 0, 0, 0, 0, 0], [0, 0, 0, 3, 0, 0, 4, 0, 1, 0, 0, 2, 0, 0, 0], [0, 0, 0, 0, 0, 0, 0, 0, 0, 5, 5, 0, 0, 0, 0], [0, 0, 0, 0, 0, 0, 0, 0, 0, 5, 5, 0, 0, 0, 0], [0, 0, 0, 0, 0, 0, 0, 0, 3, 0, 0, 4, 0, 0, 0], [0, 0, 0, 0, 0, 0, 0, 0, 0, 0, 0, 0, 0, 0, 0]], "steps": [[[0, 0, 0, 0, 0, 0, 0, 0, 0, 0, 0, 0, 0, 0, 0], [0, 0, 0, 0, 0, 0, 0, 0, 0, 0, 0, 0, 0, 0, 0], [0, 0, 0, 5, 5, 0, 0, 0, 0, 0, 0, 0, 0, 0, 0], [0, 0, 0, 5, 5, 0, 0, 0, 0, 0, 0, 0, 0, 0, 0], [0, 0, 0, 0, 0, 0, 0, 0, 5, 5, 0, 0, 0, 0, 0], [0, 0, 0, 0, 0, 0, 0, 0, 5, 5, 0, 0, 0, 0, 0], [0, 0, 0, 0, 0, 0, 0, 0, 0, 0, 0, 0, 0, 0, 0], [0, 0, 0, 0, 0, 0, 0, 0, 0, 0, 0, 0, 0, 0, 0], [0, 0, 0, 0, 5, 5, 0, 0, 0, 0, 0, 0, 0, 0, 0], [0, 0, 0, 0, 5, 5, 0, 0, 0, 0, 0, 0, 0, 0, 0], [0, 0, 0, 0, 0, 0, 0, 0, 0, 0, 0, 0, 0, 0, 0], [0, 0, 0, 0, 0, 0, 0, 0, 0, 5, 5, 0, 0, 0, 0], [0, 0, 0, 0, 0, 0, 0, 0, 0, 5, 5, 0, 0, 0, 0], [0, 0, 0, 0, 0, 0, 0, 0, 0, 0, 0, 0, 0, 0, 0], [0, 0, 0, 0, 0, 0, 0, 0, 0, 0, 0, 0, 0, 0, 0]], [[0, 0, 0, 0, 0, 0, 0, 0, 0, 0, 0, 0, 0, 0, 0], [0, 0, 0, 0, 0, 0, 0, 0, 0, 0, 0, 0, 0, 0, 0], [0, 0, 0, 5, 5, 0, 0, 0, 0, 0, 0, 0, 0, 0, 0], [0, 0, 0, 5, 5, 0, 0, 0, 0, 0, 0, 0, 0, 0, 0], [0, 0, 0, 0, 0, 0, 0, 0, 5, 5, 0, 0, 0, 0, 0], [0, 0, 0, 0, 0, 0, 0, 0, 5, 5, 0, 0, 0, 0, 0], [0, 0, 0, 0, 0, 0, 0, 0, 0, 0, 0, 0, 0, 0, 0], [0, 0, 0, 0, 0, 0, 0, 0, 0, 0, 0, 0, 0, 0, 0], [0, 0, 0, 0, 5, 5, 0, 0, 0, 0, 0, 0, 0, 0, 0], [0, 0, 0, 0, 5, 5, 0, 0, 0, 0, 0, 0, 0, 0, 0], [0, 0, 0, 0, 0, 0, 0, 0, 0, 0, 0, 0, 0, 0, 0], [0, 0, 0, 0, 0, 0, 0, 0, 0, 5, 5, 0, 0, 0, 0], [0, 0, 0, 0, 0, 0, 0, 0, 0, 5, 5, 0, 0, 0, 0], [0, 0, 0, 0, 0, 0, 0, 0, 0, 0, 0, 0, 0, 0, 0], [0, 0, 0, 0, 0, 0, 0, 0, 0, 0, 0, 0, 0, 0, 0]], [[0, 0, 0, 0, 0, 0, 0, 0, 0, 0, 0, 0, 0, 0, 0], [0, 0, 0, 0, 0, 0, 0, 0, 0, 0, 0, 0, 0, 0, 0], [0, 0, 0, 5, 5, 0, 0, 0, 0, 0, 0, 0, 0, 0, 0], [0, 0, 0, 5, 5, 0, 0, 0, 0, 0, 0, 0, 0, 0, 0], [0, 0, 0, 0, 0, 0, 0, 0, 5, 5, 0, 0, 0, 0, 0], [0, 0, 0, 0, 0, 0, 0, 0, 5, 5, 0, 0, 0, 0, 0], [0, 0, 0, 0, 0, 0, 0, 0, 0, 0, 0, 0, 0, 0, 0], [0, 0, 0, 0, 0, 0, 0, 0, 0, 0, 0, 0, 0, 0, 0], [0, 0, 0, 0, 5, 5, 0, 0, 0, 0, 0, 0, 0, 0, 0], [0, 0, 0, 0, 5, 5, 0, 0, 0, 0, 0, 0, 0, 0, 0], [0, 0, 0, 0, 0, 0, 0, 0, 0, 0, 0, 0, 0, 0, 0], [0, 0, 0, 0, 0, 0, 0, 0, 0, 5, 5, 0, 0, 0, 0], [0, 0, 0, 0, 0, 0, 0, 0, 0, 5, 5, 0, 0, 0, 0], [0, 0, 0, 0, 0, 0, 0, 0, 0, 0, 0, 0, 0, 0, 0], [0, 0, 0, 0, 0, 0, 0, 0, 0, 0, 0, 0, 0, 0, 0]], [[0, 0, 0, 0, 0, 0, 0, 0, 0, 0, 0, 0, 0, 0, 0], [0, 0, 0, 0, 0, 0, 0, 0, 0, 0, 0, 0, 0, 0, 0], [0, 0, 0, 5, 5, 0, 0, 0, 0, 0, 0, 0, 0, 0, 0], [0, 0, 0, 5, 5, 0, 0, 0, 0, 0, 0, 0, 0, 0, 0], [0, 0, 3, 0, 0, 0, 0, 0, 5, 5, 0, 0, 0, 0, 0], [0, 0, 0, 0, 0, 0, 0, 0, 5, 5, 0, 0, 0, 0, 0], [0, 0, 0, 0, 0, 0, 0, 0, 0, 0, 0, 0, 0, 0, 0], [0, 0, 0, 0, 0, 0, 0, 0, 0, 0, 0, 0, 0, 0, 0], [0, 0, 0, 0, 5, 5, 0, 0, 0, 0, 0, 0, 0, 0, 0], [0, 0, 0, 0, 5, 5, 0, 0, 0, 0, 0, 0, 0, 0, 0], [0, 0, 0, 0, 0, 0, 4, 0, 0, 0, 0, 0, 0, 0, 0], [0, 0, 0, 0, 0, 0, 0, 0, 0, 5, 5, 0, 0, 0, 0], [0, 0, 0, 0, 0, 0, 0, 0, 0, 5, 5, 0, 0, 0, 0], [0, 0, 0, 0, 0, 0, 0, 0, 0, 0, 0, 4, 0, 0, 0], [0, 0, 0, 0, 0, 0, 0, 0, 0, 0, 0, 0, 0, 0, 0]], [[0, 0, 0, 0, 0, 0, 0, 0, 0, 0, 0, 0, 0, 0, 0], [0, 0, 0, 0, 0, 0, 0, 0, 0, 0, 0, 0, 0, 0, 0], [0, 0, 0, 5, 5, 0, 0, 0, 0, 0, 0, 0, 0, 0, 0], [0, 0, 0, 5, 5, 0, 0, 0, 0, 0, 0, 0, 0, 0, 0], [0, 0, 3, 0, 0, 4, 0, 0, 5, 5, 0, 0, 0, 0, 0], [0, 0, 0, 0, 0, 0, 0, 0, 5, 5, 0, 0, 0, 0, 0], [0, 0, 0, 0, 0, 0, 0, 3, 0, 0, 4, 0, 0, 0, 0], [0, 0, 0, 0, 0, 0, 2, 0, 0, 0, 0, 0, 0, 0, 0], [0, 0, 0, 0, 5, 5, 0, 0, 0, 0, 0, 0, 0, 0, 0], [0, 0, 0, 0, 5, 5, 0, 0, 0, 0, 0, 0, 0, 0, 0], [0, 0, 0, 0, 0, 0, 4, 0, 0, 0, 0, 2, 0, 0, 0], [0, 0, 0, 0, 0, 0, 0, 0, 0, 5, 5, 0, 0, 0, 0], [0, 0, 0, 0, 0, 0, 0, 0, 0, 5, 5, 0, 0, 0, 0], [0, 0, 0, 0, 0, 0, 0, 0, 0, 0, 0, 4, 0, 0, 0], [0, 0, 0, 0, 0, 0, 0, 0, 0, 0, 0, 0, 0, 0, 0]], [[0, 0, 0, 0, 0, 0, 0, 0, 0, 0, 0, 0, 0, 0, 0], [0, 0, 1, 0, 0, 2, 0, 0, 0, 0, 0, 0, 0, 0, 0], [0, 0, 0, 5, 5, 0, 0, 0, 0, 0, 0, 0, 0, 0, 0], [0, 0, 0, 5, 5, 0, 0, 1, 0, 0, 0, 0, 0, 0, 0], [0, 0, 3, 0, 0, 4, 0, 0, 5, 5, 0, 0, 0, 0, 0], [0, 0, 0, 0, 0, 0, 0, 0, 5, 5, 0, 0, 0, 0, 0], [0, 0, 0, 0, 0, 0, 0, 3, 0, 0, 4, 0, 0, 0, 0], [0, 0, 0, 1, 0, 0, 2, 0, 0, 0, 0, 0, 0, 0, 0], [0, 0, 0, 0, 5, 5, 0, 0, 0, 0, 0, 0, 0, 0, 0], [0, 0, 0, 0, 5, 5, 0, 0, 0, 0, 0, 0, 0, 0, 0], [0, 0, 0, 3, 0, 0, 4, 0, 1, 0, 0, 2, 0, 0, 0], [0, 0, 0, 0, 0, 0, 0, 0, 0, 5, 5, 0, 0, 0, 0], [0, 0, 0, 0, 0, 0, 0, 0, 0, 5, 5, 0, 0, 0, 0], [0, 0, 0, 0, 0, 0, 0, 0, 0, 0, 0, 4, 0, 0, 0], [0, 0, 0, 0, 0, 0, 0, 0, 0, 0, 0, 0, 0, 0, 0]], [[0, 0, 0, 0, 0, 0, 0, 0, 0, 0, 0, 0, 0, 0, 0], [0, 0, 1, 0, 0, 2, 0, 0, 0, 0, 0, 0, 0, 0, 0], [0, 0, 0, 5, 5, 0, 0, 0, 0, 0, 0, 0, 0, 0, 0], [0, 0, 0, 5, 5, 0, 0, 1, 0, 0, 0, 0, 0, 0, 0], [0, 0, 3, 0, 0, 4, 0, 0, 5, 5, 0, 0, 0, 0, 0], [0, 0, 0, 0, 0, 0, 0, 0, 5, 5, 0, 0, 0, 0, 0], [0, 0, 0, 0, 0, 0, 0, 3, 0, 0, 4, 0, 0, 0, 0], [0, 0, 0, 1, 0, 0, 2, 0, 0, 0, 0, 0, 0, 0, 0], [0, 0, 0, 0, 5, 5, 0, 0, 0, 0, 0, 0, 0, 0, 0], [0, 0, 0, 0, 5, 5, 0, 0, 0, 0, 0, 0, 0, 0, 0], [0, 0, 0, 3, 0, 0, 4, 0, 1, 0, 0, 2, 0, 0, 0], [0, 0, 0, 0, 0, 0, 0, 0, 0, 5, 5, 0, 0, 0, 0], [0, 0, 0, 0, 0, 0, 0, 0, 0, 5, 5, 0, 0, 0, 0], [0, 0, 0, 0, 0, 0, 0, 0, 0, 0, 0, 4, 0, 0, 0], [0, 0, 0, 0, 0, 0, 0, 0, 0, 0, 0, 0, 0, 0, 0]], [[0, 0, 0, 0, 0, 0, 0, 0, 0, 0, 0, 0, 0, 0, 0], [0, 0, 1, 0, 0, 2, 0, 0, 0, 0, 0, 0, 0, 0, 0], [0, 0, 0, 5, 5, 0, 0, 0, 0, 0, 0, 0, 0, 0, 0], [0, 0, 0, 5, 5, 0, 0, 1, 0, 0, 2, 0, 0, 0, 0], [0, 0, 3, 0, 0, 4, 0, 0, 5, 5, 0, 0, 0, 0, 0], [0, 0, 0, 0, 0, 0, 0, 0, 5, 5, 0, 0, 0, 0, 0], [0, 0, 0, 0, 0, 0, 0, 3, 0, 0, 4, 0, 0, 0, 0], [0, 0, 0, 1, 0, 0, 2, 0, 0, 0, 0, 0, 0, 0, 0], [0, 0, 0, 0, 5, 5, 0, 0, 0, 0, 0, 0, 0, 0, 0], [0, 0, 0, 0, 5, 5, 0, 0, 0, 0, 0, 0, 0, 0, 0], [0, 0, 0, 3, 0, 0, 4, 0, 1, 0, 0, 2, 0, 0, 0], [0, 0, 0, 0, 0, 0, 0, 0, 0, 5, 5, 0, 0, 0, 0], [0, 0, 0, 0, 0, 0, 0, 0, 0, 5, 5, 0, 0, 0, 0], [0, 0, 0, 0, 0, 0, 0, 0, 3, 0, 0, 4, 0, 0, 0], [0, 0, 0, 0, 0, 0, 0, 0, 0, 0, 0, 0, 0, 0, 0]], [[0, 0, 0, 0, 0, 0, 0, 0, 0, 0, 0, 0, 0, 0, 0], [0, 0, 1, 0, 0, 2, 0, 0, 0, 0, 0, 0, 0, 0, 0], [0, 0, 0, 5, 5, 0, 0, 0, 0, 0, 0, 0, 0, 0, 0], [0, 0, 0, 5, 5, 0, 0, 1, 0, 0, 2, 0, 0, 0, 0], [0, 0, 3, 0, 0, 4, 0, 0, 5, 5, 0, 0, 0, 0, 0], [0, 0, 0, 0, 0, 0, 0, 0, 5, 5, 0, 0, 0, 0, 0], [0, 0, 0, 0, 0, 0, 0, 3, 0, 0, 4, 0, 0, 0, 0], [0, 0, 0, 1, 0, 0, 2, 0, 0, 0, 0, 0, 0, 0, 0], [0, 0, 0, 0, 5, 5, 0, 0, 0, 0, 0, 0, 0, 0, 0], [0, 0, 0, 0, 5, 5, 0, 0, 0, 0, 0, 0, 0, 0, 0], [0, 0, 0, 3, 0, 0, 4, 0, 1, 0, 0, 2, 0, 0, 0], [0, 0, 0, 0, 0, 0, 0, 0, 0, 5, 5, 0, 0, 0, 0], [0, 0, 0, 0, 0, 0, 0, 0, 0, 5, 5, 0, 0, 0, 0], [0, 0, 0, 0, 0, 0, 0, 0, 3, 0, 0, 4, 0, 0, 0], [0, 0, 0, 0, 0, 0, 0, 0, 0, 0, 0, 0, 0, 0, 0]], [[0, 0, 0, 0, 0, 0, 0, 0, 0, 0, 0, 0, 0, 0, 0], [0, 0, 1, 0, 0, 2, 0, 0, 0, 0, 0, 0, 0, 0, 0], [0, 0, 0, 5, 5, 0, 0, 0, 0, 0, 0, 0, 0, 0, 0], [0, 0, 0, 5, 5, 0, 0, 1, 0, 0, 2, 0, 0, 0, 0], [0, 0, 3, 0, 0, 4, 0, 0, 5, 5, 0, 0, 0, 0, 0], [0, 0, 0, 0, 0, 0, 0, 0, 5, 5, 0, 0, 0, 0, 0], [0, 0, 0, 0, 0, 0, 0, 3, 0, 0, 4, 0, 0, 0, 0], [0, 0, 0, 1, 0, 0, 2, 0, 0, 0, 0, 0, 0, 0, 0], [0, 0, 0, 0, 5, 5, 0, 0, 0, 0, 0, 0, 0, 0, 0], [0, 0, 0, 0, 5, 5, 0, 0, 0, 0, 0, 0, 0, 0, 0], [0, 0, 0, 3, 0, 0, 4, 0, 1, 0, 0, 2, 0, 0, 0], [0, 0, 0, 0, 0, 0, 0, 0, 0, 5, 5, 0, 0, 0, 0], [0, 0, 0, 0, 0, 0, 0, 0, 0, 5, 5, 0, 0, 0, 0], [0, 0, 0, 0, 0, 0, 0, 0, 3, 0, 0, 4, 0, 0, 0], [0, 0, 0, 0, 0, 0, 0, 0, 0, 0, 0, 0, 0, 0, 0]], [[0, 0, 0, 0, 0, 0, 0, 0, 0, 0, 0, 0, 0, 0, 0], [0, 0, 1, 0, 0, 2, 0, 0, 0, 0, 0, 0, 0, 0, 0], [0, 0, 0, 5, 5, 0, 0, 0, 0, 0, 0, 0, 0, 0, 0], [0, 0, 0, 5, 5, 0, 0, 1, 0, 0, 2, 0, 0, 0, 0], [0, 0, 3, 0, 0, 4, 0, 0, 5, 5, 0, 0, 0, 0, 0], [0, 0, 0, 0, 0, 0, 0, 0, 5, 5, 0, 0, 0, 0, 0], [0, 0, 0, 0, 0, 0, 0, 3, 0, 0, 4, 0, 0, 0, 0], [0, 0, 0, 1, 0, 0, 2, 0, 0, 0, 0, 0, 0, 0, 0], [0, 0, 0, 0, 5, 5, 0, 0, 0, 0, 0, 0, 0, 0, 0], [0, 0, 0, 0, 5, 5, 0, 0, 0, 0, 0, 0, 0, 0, 0], [0, 0, 0, 3, 0, 0, 4, 0, 1, 0, 0, 2, 0, 0, 0], [0, 0, 0, 0, 0, 0, 0, 0, 0, 5, 5, 0, 0, 0, 0], [0, 0, 0, 0, 0, 0, 0, 0, 0, 5, 5, 0, 0, 0, 0], [0, 0, 0, 0, 0, 0, 0, 0, 3, 0, 0, 4, 0, 0, 0], [0, 0, 0, 0, 0, 0, 0, 0, 0, 0, 0, 0, 0, 0, 0]], [[0, 0, 0, 0, 0, 0, 0, 0, 0, 0, 0, 0, 0, 0, 0], [0, 0, 1, 0, 0, 2, 0, 0, 0, 0, 0, 0, 0, 0, 0], [0, 0, 0, 5, 5, 0, 0, 0, 0, 0, 0, 0, 0, 0, 0], [0, 0, 0, 5, 5, 0, 0, 1, 0, 0, 2, 0, 0, 0, 0], [0, 0, 3, 0, 0, 4, 0, 0, 5, 5, 0, 0, 0, 0, 0], [0, 0, 0, 0, 0, 0, 0, 0, 5, 5, 0, 0, 0, 0, 0], [0, 0, 0, 0, 0, 0, 0, 3, 0, 0, 4, 0, 0, 0, 0], [0, 0, 0, 1, 0, 0, 2, 0, 0, 0, 0, 0, 0, 0, 0], [0, 0, 0, 0, 5, 5, 0, 0, 0, 0, 0, 0, 0, 0, 0], [0, 0, 0, 0, 5, 5, 0, 0, 0, 0, 0, 0, 0, 0, 0], [0, 0, 0, 3, 0, 0, 4, 0, 1, 0, 0, 2, 0, 0, 0], [0, 0, 0, 0, 0, 0, 0, 0, 0, 5, 5, 0, 0, 0, 0], [0, 0, 0, 0, 0, 0, 0, 0, 0, 5, 5, 0, 0, 0, 0], [0, 0, 0, 0, 0, 0, 0, 0, 3, 0, 0, 4, 0, 0, 0], [0, 0, 0, 0, 0, 0, 0, 0, 0, 0, 0, 0, 0, 0, 0]], [[0, 0, 0, 0, 0, 0, 0, 0, 0, 0, 0, 0, 0, 0, 0], [0, 0, 1, 0, 0, 2, 0, 0, 0, 0, 0, 0, 0, 0, 0], [0, 0, 0, 5, 5, 0, 0, 0, 0, 0, 0, 0, 0, 0, 0], [0, 0, 0, 5, 5, 0, 0, 1, 0, 0, 2, 0, 0, 0, 0], [0, 0, 3, 0, 0, 4, 0, 0, 5, 5, 0, 0, 0, 0, 0], [0, 0, 0, 0, 0, 0, 0, 0, 5, 5, 0, 0, 0, 0, 0], [0, 0, 0, 0, 0, 0, 0, 3, 0, 0, 4, 0, 0, 0, 0], [0, 0, 0, 1, 0, 0, 2, 0, 0, 0, 0, 0, 0, 0, 0], [0, 0, 0, 0, 5, 5, 0, 0, 0, 0, 0, 0, 0, 0, 0], [0, 0, 0, 0, 5, 5, 0, 0, 0, 0, 0, 0, 0, 0, 0], [0, 0, 0, 3, 0, 0, 4, 0, 1, 0, 0, 2, 0, 0, 0], [0, 0, 0, 0, 0, 0, 0, 0, 0, 5, 5, 0, 0, 0, 0], [0, 0, 0, 0, 0, 0, 0, 0, 0, 5, 5, 0, 0, 0, 0], [0, 0, 0, 0, 0, 0, 0, 0, 3, 0, 0, 4, 0, 0, 0], [0, 0, 0, 0, 0, 0, 0, 0, 0, 0, 0, 0, 0, 0, 0]], [[0, 0, 0, 0, 0, 0, 0, 0, 0, 0, 0, 0, 0, 0, 0], [0, 0, 1, 0, 0, 2, 0, 0, 0, 0, 0, 0, 0, 0, 0], [0, 0, 0, 5, 5, 0, 0, 0, 0, 0, 0, 0, 0, 0, 0], [0, 0, 0, 5, 5, 0, 0, 1, 0, 0, 2, 0, 0, 0, 0], [0, 0, 3, 0, 0, 4, 0, 0, 5, 5, 0, 0, 0, 0, 0], [0, 0, 0, 0, 0, 0, 0, 0, 5, 5, 0, 0, 0, 0, 0], [0, 0, 0, 0, 0, 0, 0, 3, 0, 0, 4, 0, 0, 0, 0], [0, 0, 0, 1, 0, 0, 2, 0, 0, 0, 0, 0, 0, 0, 0], [0, 0, 0, 0, 5, 5, 0, 0, 0, 0, 0, 0, 0, 0, 0], [0, 0, 0, 0, 5, 5, 0, 0, 0, 0, 0, 0, 0, 0, 0], [0, 0, 0, 3, 0, 0, 4, 0, 1, 0, 0, 2, 0, 0, 0], [0, 0, 0, 0, 0, 0, 0, 0, 0, 5, 5, 0, 0, 0, 0], [0, 0, 0, 0, 0, 0, 0, 0, 0, 5, 5, 0, 0, 0, 0], [0, 0, 0, 0, 0, 0, 0, 0, 3, 0, 0, 4, 0, 0, 0], [0, 0, 0, 0, 0, 0, 0, 0, 0, 0, 0, 0, 0, 0, 0]], [[0, 0, 0, 0, 0, 0, 0, 0, 0, 0, 0, 0, 0, 0, 0], [0, 0, 1, 0, 0, 2, 0, 0, 0, 0, 0, 0, 0, 0, 0], [0, 0, 0, 5, 5, 0, 0, 0, 0, 0, 0, 0, 0, 0, 0], [0, 0, 0, 5, 5, 0, 0, 1, 0, 0, 2, 0, 0, 0, 0], [0, 0, 3, 0, 0, 4, 0, 0, 5, 5, 0, 0, 0, 0, 0], [0, 0, 0, 0, 0, 0, 0, 0, 5, 5, 0, 0, 0, 0, 0], [0, 0, 0, 0, 0, 0, 0, 3, 0, 0, 4, 0, 0, 0, 0], [0, 0, 0, 1, 0, 0, 2, 0, 0, 0, 0, 0, 0, 0, 0], [0, 0, 0, 0, 5, 5, 0, 0, 0, 0, 0, 0, 0, 0, 0], [0, 0, 0, 0, 5, 5, 0, 0, 0, 0, 0, 0, 0, 0, 0], [0, 0, 0, 3, 0, 0, 4, 0, 1, 0, 0, 2, 0, 0, 0], [0, 0, 0, 0, 0, 0, 0, 0, 0, 5, 5, 0, 0, 0, 0], [0, 0, 0, 0, 0, 0, 0, 0, 0, 5, 5, 0, 0, 0, 0], [0, 0, 0, 0, 0, 0, 0, 0, 3, 0, 0, 4, 0, 0, 0], [0, 0, 0, 0, 0, 0, 0, 0, 0, 0, 0, 0, 0, 0, 0]], [[0, 0, 0, 0, 0, 0, 0, 0, 0, 0, 0, 0, 0, 0, 0], [0, 0, 1, 0, 0, 2, 0, 0, 0, 0, 0, 0, 0, 0, 0], [0, 0, 0, 5, 5, 0, 0, 0, 0, 0, 0, 0, 0, 0, 0], [0, 0, 0, 5, 5, 0, 0, 1, 0, 0, 2, 0, 0, 0, 0], [0, 0, 3, 0, 0, 4, 0, 0, 5, 5, 0, 0, 0, 0, 0], [0, 0, 0, 0, 0, 0, 0, 0, 5, 5, 0, 0, 0, 0, 0], [0, 0, 0, 0, 0, 0, 0, 3, 0, 0, 4, 0, 0, 0, 0], [0, 0, 0, 1, 0, 0, 2, 0, 0, 0, 0, 0, 0, 0, 0], [0, 0, 0, 0, 5, 5, 0, 0, 0, 0, 0, 0, 0, 0, 0], [0, 0, 0, 0, 5, 5, 0, 0, 0, 0, 0, 0, 0, 0, 0], [0, 0, 0, 3, 0, 0, 4, 0, 1, 0, 0, 2, 0, 0, 0], [0, 0, 0, 0, 0, 0, 0, 0, 0, 5, 5, 0, 0, 0, 0], [0, 0, 0, 0, 0, 0, 0, 0, 0, 5, 5, 0, 0, 0, 0], [0, 0, 0, 0, 0, 0, 0, 0, 3, 0, 0, 4, 0, 0, 0], [0, 0, 0, 0, 0, 0, 0, 0, 0, 0, 0, 0, 0, 0, 0]], [[0, 0, 0, 0, 0, 0, 0, 0, 0, 0, 0, 0, 0, 0, 0], [0, 0, 1, 0, 0, 2, 0, 0, 0, 0, 0, 0, 0, 0, 0], [0, 0, 0, 5, 5, 0, 0, 0, 0, 0, 0, 0, 0, 0, 0], [0, 0, 0, 5, 5, 0, 0, 1, 0, 0, 2, 0, 0, 0, 0], [0, 0, 3, 0, 0, 4, 0, 0, 5, 5, 0, 0, 0, 0, 0], [0, 0, 0, 0, 0, 0, 0, 0, 5, 5, 0, 0, 0, 0, 0], [0, 0, 0, 0, 0, 0, 0, 3, 0, 0, 4, 0, 0, 0, 0], [0, 0, 0, 1, 0, 0, 2, 0, 0, 0, 0, 0, 0, 0, 0], [0, 0, 0, 0, 5, 5, 0, 0, 0, 0, 0, 0, 0, 0, 0], [0, 0, 0, 0, 5, 5, 0, 0, 0, 0, 0, 0, 0, 0, 0], [0, 0, 0, 3, 0, 0, 4, 0, 1, 0, 0, 2, 0, 0, 0], [0, 0, 0, 0, 0, 0, 0, 0, 0, 5, 5, 0, 0, 0, 0], [0, 0, 0, 0, 0, 0, 0, 0, 0, 5, 5, 0, 0, 0, 0], [0, 0, 0, 0, 0, 0, 0, 0, 3, 0, 0, 4, 0, 0, 0], [0, 0, 0, 0, 0, 0, 0, 0, 0, 0, 0, 0, 0, 0, 0]], [[0, 0, 0, 0, 0, 0, 0, 0, 0, 0, 0, 0, 0, 0, 0], [0, 0, 1, 0, 0, 2, 0, 0, 0, 0, 0, 0, 0, 0, 0], [0, 0, 0, 5, 5, 0, 0, 0, 0, 0, 0, 0, 0, 0, 0], [0, 0, 0, 5, 5, 0, 0, 1, 0, 0, 2, 0, 0, 0, 0], [0, 0, 3, 0, 0, 4, 0, 0, 5, 5, 0, 0, 0, 0, 0], [0, 0, 0, 0, 0, 0, 0, 0, 5, 5, 0, 0, 0, 0, 0], [0, 0, 0, 0, 0, 0, 0, 3, 0, 0, 4, 0, 0, 0, 0], [0, 0, 0, 1, 0, 0, 2, 0, 0, 0, 0, 0, 0, 0, 0], [0, 0, 0, 0, 5, 5, 0, 0, 0, 0, 0, 0, 0, 0, 0], [0, 0, 0, 0, 5, 5, 0, 0, 0, 0, 0, 0, 0, 0, 0], [0, 0, 0, 3, 0, 0, 4, 0, 1, 0, 0, 2, 0, 0, 0], [0, 0, 0, 0, 0, 0, 0, 0, 0, 5, 5, 0, 0, 0, 0], [0, 0, 0, 0, 0, 0, 0, 0, 0, 5, 5, 0, 0, 0, 0], [0, 0, 0, 0, 0, 0, 0, 0, 3, 0, 0, 4, 0, 0, 0], [0, 0, 0, 0, 0, 0, 0, 0, 0, 0, 0, 0, 0, 0, 0]], [[0, 0, 0, 0, 0, 0, 0, 0, 0, 0, 0, 0, 0, 0, 0], [0, 0, 1, 0, 0, 2, 0, 0, 0, 0, 0, 0, 0, 0, 0], [0, 0, 0, 5, 5, 0, 0, 0, 0, 0, 0, 0, 0, 0, 0], [0, 0, 0, 5, 5, 0, 0, 1, 0, 0, 2, 0, 0, 0, 0], [0, 0, 3, 0, 0, 4, 0, 0, 5, 5, 0, 0, 0, 0, 0], [0, 0, 0, 0, 0, 0, 0, 0, 5, 5, 0, 0, 0, 0, 0], [0, 0, 0, 0, 0, 0, 0, 3, 0, 0, 4, 0, 0, 0, 0], [0, 0, 0, 1, 0, 0, 2, 0, 0, 0, 0, 0, 0, 0, 0], [0, 0, 0, 0, 5, 5, 0, 0, 0, 0, 0, 0, 0, 0, 0], [0, 0, 0, 0, 5, 5, 0, 0, 0, 0, 0, 0, 0, 0, 0], [0, 0, 0, 3, 0, 0, 4, 0, 1, 0, 0, 2, 0, 0, 0], [0, 0, 0, 0, 0, 0, 0, 0, 0, 5, 5, 0, 0, 0, 0], [0, 0, 0, 0, 0, 0, 0, 0, 0, 5, 5, 0, 0, 0, 0], [0, 0, 0, 0, 0, 0, 0, 0, 3, 0, 0, 4, 0, 0, 0], [0, 0, 0, 0, 0, 0, 0, 0, 0, 0, 0, 0, 0, 0, 0]], [[0, 0, 0, 0, 0, 0, 0, 0, 0, 0, 0, 0, 0, 0, 0], [0, 0, 1, 0, 0, 2, 0, 0, 0, 0, 0, 0, 0, 0, 0], [0, 0, 0, 5, 5, 0, 0, 0, 0, 0, 0, 0, 0, 0, 0], [0, 0, 0, 5, 5, 0, 0, 1, 0, 0, 2, 0, 0, 0, 0], [0, 0, 3, 0, 0, 4, 0, 0, 5, 5, 0, 0, 0, 0, 0], [0, 0, 0, 0, 0, 0, 0, 0, 5, 5, 0, 0, 0, 0, 0], [0, 0, 0, 0, 0, 0, 0, 3, 0, 0, 4, 0, 0, 0, 0], [0, 0, 0, 1, 0, 0, 2, 0, 0, 0, 0, 0, 0, 0, 0], [0, 0, 0, 0, 5, 5, 0, 0, 0, 0, 0, 0, 0, 0, 0], [0, 0, 0, 0, 5, 5, 0, 0, 0, 0, 0, 0, 0, 0, 0], [0, 0, 0, 3, 0, 0, 4, 0, 1, 0, 0, 2, 0, 0, 0], [0, 0, 0, 0, 0, 0, 0, 0, 0, 5, 5, 0, 0, 0, 0], [0, 0, 0, 0, 0, 0, 0, 0, 0, 5, 5, 0, 0, 0, 0], [0, 0, 0, 0, 0, 0, 0, 0, 3, 0, 0, 4, 0, 0, 0], [0, 0, 0, 0, 0, 0, 0, 0, 0, 0, 0, 0, 0, 0, 0]], [[0, 0, 0, 0, 0, 0, 0, 0, 0, 0, 0, 0, 0, 0, 0], [0, 0, 1, 0, 0, 2, 0, 0, 0, 0, 0, 0, 0, 0, 0], [0, 0, 0, 5, 5, 0, 0, 0, 0, 0, 0, 0, 0, 0, 0], [0, 0, 0, 5, 5, 0, 0, 1, 0, 0, 2, 0, 0, 0, 0], [0, 0, 3, 0, 0, 4, 0, 0, 5, 5, 0, 0, 0, 0, 0], [0, 0, 0, 0, 0, 0, 0, 0, 5, 5, 0, 0, 0, 0, 0], [0, 0, 0, 0, 0, 0, 0, 3, 0, 0, 4, 0, 0, 0, 0], [0, 0, 0, 1, 0, 0, 2, 0, 0, 0, 0, 0, 0, 0, 0], [0, 0, 0, 0, 5, 5, 0, 0, 0, 0, 0, 0, 0, 0, 0], [0, 0, 0, 0, 5, 5, 0, 0, 0, 0, 0, 0, 0, 0, 0], [0, 0, 0, 3, 0, 0, 4, 0, 1, 0, 0, 2, 0, 0, 0], [0, 0, 0, 0, 0, 0, 0, 0, 0, 5, 5, 0, 0, 0, 0], [0, 0, 0, 0, 0, 0, 0, 0, 0, 5, 5, 0, 0, 0, 0], [0, 0, 0, 0, 0, 0, 0, 0, 3, 0, 0, 4, 0, 0, 0], [0, 0, 0, 0, 0, 0, 0, 0, 0, 0, 0, 0, 0, 0, 0]], [[0, 0, 0, 0, 0, 0, 0, 0, 0, 0, 0, 0, 0, 0, 0], [0, 0, 1, 0, 0, 2, 0, 0, 0, 0, 0, 0, 0, 0, 0], [0, 0, 0, 5, 5, 0, 0, 0, 0, 0, 0, 0, 0, 0, 0], [0, 0, 0, 5, 5, 0, 0, 1, 0, 0, 2, 0, 0, 0, 0], [0, 0, 3, 0, 0, 4, 0, 0, 5, 5, 0, 0, 0, 0, 0], [0, 0, 0, 0, 0, 0, 0, 0, 5, 5, 0, 0, 0, 0, 0], [0, 0, 0, 0, 0, 0, 0, 3, 0, 0, 4, 0, 0, 0, 0], [0, 0, 0, 1, 0, 0, 2, 0, 0, 0, 0, 0, 0, 0, 0], [0, 0, 0, 0, 5, 5, 0, 0, 0, 0, 0, 0, 0, 0, 0], [0, 0, 0, 0, 5, 5, 0, 0, 0, 0, 0, 0, 0, 0, 0], [0, 0, 0, 3, 0, 0, 4, 0, 1, 0, 0, 2, 0, 0, 0], [0, 0, 0, 0, 0, 0, 0, 0, 0, 5, 5, 0, 0, 0, 0], [0, 0, 0, 0, 0, 0, 0, 0, 0, 5, 5, 0, 0, 0, 0], [0, 0, 0, 0, 0, 0, 0, 0, 3, 0, 0, 4, 0, 0, 0], [0, 0, 0, 0, 0, 0, 0, 0, 0, 0, 0, 0, 0, 0, 0]], [[0, 0, 0, 0, 0, 0, 0, 0, 0, 0, 0, 0, 0, 0, 0], [0, 0, 1, 0, 0, 2, 0, 0, 0, 0, 0, 0, 0, 0, 0], [0, 0, 0, 5, 5, 0, 0, 0, 0, 0, 0, 0, 0, 0, 0], [0, 0, 0, 5, 5, 0, 0, 1, 0, 0, 2, 0, 0, 0, 0], [0, 0, 3, 0, 0, 4, 0, 0, 5, 5, 0, 0, 0, 0, 0], [0, 0, 0, 0, 0, 0, 0, 0, 5, 5, 0, 0, 0, 0, 0], [0, 0, 0, 0, 0, 0, 0, 3, 0, 0, 4, 0, 0, 0, 0], [0, 0, 0, 1, 0, 0, 2, 0, 0, 0, 0, 0, 0, 0, 0], [0, 0, 0, 0, 5, 5, 0, 0, 0, 0, 0, 0, 0, 0, 0], [0, 0, 0, 0, 5, 5, 0, 0, 0, 0, 0, 0, 0, 0, 0], [0, 0, 0, 3, 0, 0, 4, 0, 1, 0, 0, 2, 0, 0, 0], [0, 0, 0, 0, 0, 0, 0, 0, 0, 5, 5, 0, 0, 0, 0], [0, 0, 0, 0, 0, 0, 0, 0, 0, 5, 5, 0, 0, 0, 0], [0, 0, 0, 0, 0, 0, 0, 0, 3, 0, 0, 4, 0, 0, 0], [0, 0, 0, 0, 0, 0, 0, 0, 0, 0, 0, 0, 0, 0, 0]], [[0, 0, 0, 0, 0, 0, 0, 0, 0, 0, 0, 0, 0, 0, 0], [0, 0, 1, 0, 0, 2, 0, 0, 0, 0, 0, 0, 0, 0, 0], [0, 0, 0, 5, 5, 0, 0, 0, 0, 0, 0, 0, 0, 0, 0], [0, 0, 0, 5, 5, 0, 0, 1, 0, 0, 2, 0, 0, 0, 0], [0, 0, 3, 0, 0, 4, 0, 0, 5, 5, 0, 0, 0, 0, 0], [0, 0, 0, 0, 0, 0, 0, 0, 5, 5, 0, 0, 0, 0, 0], [0, 0, 0, 0, 0, 0, 0, 3, 0, 0, 4, 0, 0, 0, 0], [0, 0, 0, 1, 0, 0, 2, 0, 0, 0, 0, 0, 0, 0, 0], [0, 0, 0, 0, 5, 5, 0, 0, 0, 0, 0, 0, 0, 0, 0], [0, 0, 0, 0, 5, 5, 0, 0, 0, 0, 0, 0, 0, 0, 0], [0, 0, 0, 3, 0, 0, 4, 0, 1, 0, 0, 2, 0, 0, 0], [0, 0, 0, 0, 0, 0, 0, 0, 0, 5, 5, 0, 0, 0, 0], [0, 0, 0, 0, 0, 0, 0, 0, 0, 5, 5, 0, 0, 0, 0], [0, 0, 0, 0, 0, 0, 0, 0, 3, 0, 0, 4, 0, 0, 0], [0, 0, 0, 0, 0, 0, 0, 0, 0, 0, 0, 0, 0, 0, 0]], [[0, 0, 0, 0, 0, 0, 0, 0, 0, 0, 0, 0, 0, 0, 0], [0, 0, 1, 0, 0, 2, 0, 0, 0, 0, 0, 0, 0, 0, 0], [0, 0, 0, 5, 5, 0, 0, 0, 0, 0, 0, 0, 0, 0, 0], [0, 0, 0, 5, 5, 0, 0, 1, 0, 0, 2, 0, 0, 0, 0], [0, 0, 3, 0, 0, 4, 0, 0, 5, 5, 0, 0, 0, 0, 0], [0, 0, 0, 0, 0, 0, 0, 0, 5, 5, 0, 0, 0, 0, 0], [0, 0, 0, 0, 0, 0, 0, 3, 0, 0, 4, 0, 0, 0, 0], [0, 0, 0, 1, 0, 0, 2, 0, 0, 0, 0, 0, 0, 0, 0], [0, 0, 0, 0, 5, 5, 0, 0, 0, 0, 0, 0, 0, 0, 0], [0, 0, 0, 0, 5, 5, 0, 0, 0, 0, 0, 0, 0, 0, 0], [0, 0, 0, 3, 0, 0, 4, 0, 1, 0, 0, 2, 0, 0, 0], [0, 0, 0, 0, 0, 0, 0, 0, 0, 5, 5, 0, 0, 0, 0], [0, 0, 0, 0, 0, 0, 0, 0, 0, 5, 5, 0, 0, 0, 0], [0, 0, 0, 0, 0, 0, 0, 0, 3, 0, 0, 4, 0, 0, 0], [0, 0, 0, 0, 0, 0, 0, 0, 0, 0, 0, 0, 0, 0, 0]], [[0, 0, 0, 0, 0, 0, 0, 0, 0, 0, 0, 0, 0, 0, 0], [0, 0, 1, 0, 0, 2, 0, 0, 0, 0, 0, 0, 0, 0, 0], [0, 0, 0, 5, 5, 0, 0, 0, 0, 0, 0, 0, 0, 0, 0], [0, 0, 0, 5, 5, 0, 0, 1, 0, 0, 2, 0, 0, 0, 0], [0, 0, 3, 0, 0, 4, 0, 0, 5, 5, 0, 0, 0, 0, 0], [0, 0, 0, 0, 0, 0, 0, 0, 5, 5, 0, 0, 0, 0, 0], [0, 0, 0, 0, 0, 0, 0, 3, 0, 0, 4, 0, 0, 0, 0], [0, 0, 0, 1, 0, 0, 2, 0, 0, 0, 0, 0, 0, 0, 0], [0, 0, 0, 0, 5, 5, 0, 0, 0, 0, 0, 0, 0, 0, 0], [0, 0, 0, 0, 5, 5, 0, 0, 0, 0, 0, 0, 0, 0, 0], [0, 0, 0, 3, 0, 0, 4, 0, 1, 0, 0, 2, 0, 0, 0], [0, 0, 0, 0, 0, 0, 0, 0, 0, 5, 5, 0, 0, 0, 0], [0, 0, 0, 0, 0, 0, 0, 0, 0, 5, 5, 0, 0, 0, 0], [0, 0, 0, 0, 0, 0, 0, 0, 3, 0, 0, 4, 0, 0, 0], [0, 0, 0, 0, 0, 0, 0, 0, 0, 0, 0, 0, 0, 0, 0]]], "accs": [92.89, 92.89, 92.89, 94.22, 96.44, 99.11, 99.11, 100.0, 100.0, 100.0, 100.0, 100.0, 100.0, 100.0, 100.0, 100.0, 100.0, 100.0, 100.0, 100.0, 100.0, 100.0, 100.0, 100.0, 100.0, 100.0], "exact": true}], "test": {"input": [[0, 0, 0, 0, 0, 0, 0, 0, 0, 0, 0, 0, 0, 0, 0], [0, 5, 5, 0, 0, 0, 0, 0, 0, 0, 0, 5, 5, 0, 0], [0, 5, 5, 0, 0, 0, 0, 0, 0, 0, 0, 5, 5, 0, 0], [0, 0, 0, 0, 0, 0, 0, 0, 0, 0, 0, 0, 0, 0, 0], [0, 0, 0, 0, 0, 5, 5, 0, 0, 0, 0, 0, 0, 0, 0], [0, 0, 0, 0, 0, 5, 5, 0, 0, 0, 0, 0, 0, 0, 0], [0, 0, 0, 0, 0, 0, 0, 0, 0, 0, 0, 0, 5, 5, 0], [0, 0, 0, 0, 0, 0, 0, 0, 0, 0, 0, 0, 5, 5, 0], [0, 0, 0, 0, 0, 0, 0, 0, 0, 0, 0, 0, 0, 0, 0], [0, 0, 0, 0, 0, 0, 0, 0, 0, 0, 0, 0, 0, 0, 0], [0, 0, 5, 5, 0, 0, 0, 0, 0, 0, 0, 0, 0, 0, 0], [0, 0, 5, 5, 0, 0, 0, 0, 0, 5, 5, 0, 0, 0, 0], [0, 0, 0, 0, 0, 0, 0, 0, 0, 5, 5, 0, 0, 0, 0], [0, 0, 0, 0, 0, 0, 0, 0, 0, 0, 0, 0, 0, 0, 0], [0, 0, 0, 0, 0, 0, 0, 0, 0, 0, 0, 0, 0, 0, 0]], "steps": [[[0, 0, 0, 0, 0, 0, 0, 0, 0, 0, 0, 0, 0, 0, 0], [0, 5, 5, 0, 0, 0, 0, 0, 0, 0, 0, 5, 5, 0, 0], [0, 5, 5, 0, 0, 0, 0, 0, 0, 0, 0, 5, 5, 0, 0], [0, 0, 0, 0, 0, 0, 0, 0, 0, 0, 0, 0, 0, 0, 0], [0, 0, 0, 0, 0, 5, 5, 0, 0, 0, 0, 0, 0, 0, 0], [0, 0, 0, 0, 0, 5, 5, 0, 0, 0, 0, 0, 0, 0, 0], [0, 0, 0, 0, 0, 0, 0, 0, 0, 0, 0, 0, 5, 5, 0], [0, 0, 0, 0, 0, 0, 0, 0, 0, 0, 0, 0, 5, 5, 0], [0, 0, 0, 0, 0, 0, 0, 0, 0, 0, 0, 0, 0, 0, 0], [0, 0, 0, 0, 0, 0, 0, 0, 0, 0, 0, 0, 0, 0, 0], [0, 0, 5, 5, 0, 0, 0, 0, 0, 0, 0, 0, 0, 0, 0], [0, 0, 5, 5, 0, 0, 0, 0, 0, 5, 5, 0, 0, 0, 0], [0, 0, 0, 0, 0, 0, 0, 0, 0, 5, 5, 0, 0, 0, 0], [0, 0, 0, 0, 0, 0, 0, 0, 0, 0, 0, 0, 0, 0, 0], [0, 0, 0, 0, 0, 0, 0, 0, 0, 0, 0, 0, 0, 0, 0]], [[0, 0, 0, 0, 0, 0, 0, 0, 0, 0, 0, 0, 0, 0, 0], [0, 5, 5, 0, 0, 0, 0, 0, 0, 0, 0, 5, 5, 0, 0], [0, 5, 5, 0, 0, 0, 0, 0, 0, 0, 0, 5, 5, 0, 0], [0, 0, 0, 0, 0, 0, 0, 0, 0, 0, 0, 0, 0, 0, 0], [0, 0, 0, 0, 0, 5, 5, 0, 0, 0, 0, 0, 0, 0, 0], [0, 0, 0, 0, 0, 5, 5, 0, 0, 0, 0, 0, 0, 0, 0], [0, 0, 0, 0, 0, 0, 0, 0, 0, 0, 0, 0, 5, 5, 0], [0, 0, 0, 0, 0, 0, 0, 0, 0, 0, 0, 0, 5, 5, 0], [0, 0, 0, 0, 0, 0, 0, 0, 0, 0, 0, 0, 0, 0, 0], [0, 0, 0, 0, 0, 0, 0, 0, 0, 0, 0, 0, 0, 0, 0], [0, 0, 5, 5, 0, 0, 0, 0, 0, 0, 0, 0, 0, 0, 0], [0, 0, 5, 5, 0, 0, 0, 0, 0, 5, 5, 0, 0, 0, 0], [0, 0, 0, 0, 0, 0, 0, 0, 0, 5, 5, 0, 0, 0, 0], [0, 0, 0, 0, 0, 0, 0, 0, 0, 0, 0, 0, 0, 0, 0], [0, 0, 0, 0, 0, 0, 0, 0, 0, 0, 0, 0, 0, 0, 0]], [[0, 0, 0, 0, 0, 0, 0, 0, 0, 0, 0, 0, 0, 0, 0], [0, 5, 5, 0, 0, 0, 0, 0, 0, 0, 0, 5, 5, 0, 0], [0, 5, 5, 0, 0, 0, 0, 0, 0, 0, 0, 5, 5, 0, 0], [0, 0, 0, 0, 0, 0, 0, 0, 0, 0, 0, 0, 0, 0, 0], [0, 0, 0, 0, 0, 5, 5, 0, 0, 0, 0, 0, 0, 0, 0], [0, 0, 0, 0, 0, 5, 5, 0, 0, 0, 0, 0, 0, 0, 0], [0, 0, 0, 0, 0, 0, 0, 0, 0, 0, 0, 0, 5, 5, 0], [0, 0, 0, 0, 0, 0, 0, 0, 0, 0, 0, 0, 5, 5, 0], [0, 0, 0, 0, 0, 0, 0, 0, 0, 0, 0, 0, 0, 0, 0], [0, 0, 0, 0, 0, 0, 0, 0, 0, 0, 0, 0, 0, 0, 0], [0, 0, 5, 5, 0, 0, 0, 0, 0, 0, 0, 0, 0, 0, 0], [0, 0, 5, 5, 0, 0, 0, 0, 0, 5, 5, 0, 0, 0, 0], [0, 0, 0, 0, 0, 0, 0, 0, 0, 5, 5, 0, 0, 0, 0], [0, 0, 0, 0, 0, 0, 0, 0, 0, 0, 0, 4, 0, 0, 0], [0, 0, 0, 0, 0, 0, 0, 0, 0, 0, 0, 0, 0, 0, 0]], [[0, 0, 0, 0, 0, 0, 0, 0, 0, 0, 0, 0, 0, 0, 0], [0, 5, 5, 0, 0, 0, 0, 0, 0, 0, 0, 5, 5, 0, 0], [0, 5, 5, 0, 0, 0, 0, 0, 0, 0, 0, 5, 5, 0, 0], [0, 0, 0, 0, 0, 0, 0, 0, 0, 0, 0, 0, 0, 0, 0], [0, 0, 0, 0, 0, 5, 5, 0, 0, 0, 0, 0, 0, 0, 0], [0, 0, 0, 0, 0, 5, 5, 0, 0, 0, 0, 0, 0, 0, 0], [0, 0, 0, 0, 3, 0, 0, 4, 0, 0, 0, 0, 5, 5, 0], [0, 0, 0, 0, 0, 0, 0, 0, 0, 0, 0, 0, 5, 5, 0], [0, 0, 0, 0, 0, 0, 0, 0, 0, 0, 0, 3, 0, 0, 4], [0, 0, 0, 0, 0, 0, 0, 0, 0, 0, 0, 0, 0, 0, 0], [0, 0, 5, 5, 0, 0, 0, 0, 1, 0, 0, 0, 0, 0, 0], [0, 0, 5, 5, 0, 0, 0, 0, 0, 5, 5, 0, 0, 0, 0], [0, 0, 0, 0, 4, 0, 0, 0, 0, 5, 5, 0, 0, 0, 0], [0, 0, 0, 0, 0, 0, 0, 0, 3, 0, 0, 4, 0, 0, 0], [0, 0, 0, 0, 0, 0, 0, 0, 0, 0, 0, 0, 0, 0, 0]], [[0, 0, 0, 2, 0, 0, 0, 0, 0, 0, 1, 0, 0, 0, 0], [0, 5, 5, 0, 0, 0, 0, 0, 0, 0, 0, 5, 5, 0, 0], [0, 5, 5, 0, 0, 0, 0, 0, 0, 0, 0, 5, 5, 0, 0], [0, 0, 0, 0, 0, 0, 0, 0, 0, 0, 3, 0, 0, 4, 0], [0, 0, 0, 0, 0, 5, 5, 0, 0, 0, 0, 0, 0, 0, 0], [0, 0, 0, 0, 0, 5, 5, 0, 0, 0, 0, 1, 0, 0, 2], [0, 0, 0, 0, 3, 0, 0, 4, 0, 0, 0, 0, 5, 5, 0], [0, 0, 0, 0, 0, 0, 0, 0, 0, 0, 0, 0, 5, 5, 0], [0, 0, 0, 0, 0, 0, 0, 0, 0, 0, 0, 3, 0, 0, 4], [0, 0, 0, 0, 0, 0, 0, 0, 0, 0, 0, 0, 0, 0, 0], [0, 0, 5, 5, 0, 0, 0, 0, 1, 0, 0, 0, 0, 0, 0], [0, 0, 5, 5, 0, 0, 0, 0, 0, 5, 5, 0, 0, 0, 0], [0, 0, 0, 0, 4, 0, 0, 0, 0, 5, 5, 0, 0, 0, 0], [0, 0, 0, 0, 0, 0, 0, 0, 3, 0, 0, 4, 0, 0, 0], [0, 0, 0, 0, 0, 0, 0, 0, 0, 0, 0, 0, 0, 0, 0]], [[0, 0, 0, 2, 0, 0, 0, 0, 0, 0, 1, 0, 0, 0, 0], [0, 5, 5, 0, 0, 0, 0, 0, 0, 0, 0, 5, 5, 0, 0], [0, 5, 5, 0, 0, 0, 0, 0, 0, 0, 0, 5, 5, 0, 0], [3, 0, 0, 4, 0, 0, 0, 0, 0, 0, 3, 0, 0, 4, 0], [0, 0, 0, 0, 0, 5, 5, 0, 0, 0, 0, 0, 0, 0, 0], [0, 0, 0, 0, 0, 5, 5, 0, 0, 0, 0, 1, 0, 0, 2], [0, 0, 0, 0, 3, 0, 0, 4, 0, 0, 0, 0, 5, 5, 0], [0, 0, 0, 0, 0, 0, 0, 0, 0, 0, 0, 0, 5, 5, 0], [0, 0, 0, 0, 0, 0, 0, 0, 0, 0, 0, 3, 0, 0, 4], [0, 1, 0, 0, 2, 0, 0, 0, 0, 0, 0, 0, 0, 0, 0], [0, 0, 5, 5, 0, 0, 0, 0, 1, 0, 0, 2, 0, 0, 0], [0, 0, 5, 5, 0, 0, 0, 0, 0, 5, 5, 0, 0, 0, 0], [0, 3, 0, 0, 4, 0, 0, 0, 0, 5, 5, 0, 0, 0, 0], [0, 0, 0, 0, 0, 0, 0, 0, 3, 0, 0, 4, 0, 0, 0], [0, 0, 0, 0, 0, 0, 0, 0, 0, 0, 0, 0, 0, 0, 0]], [[0, 0, 0, 2, 0, 0, 0, 0, 0, 0, 1, 0, 0, 2, 0], [0, 5, 5, 0, 0, 0, 0, 0, 0, 0, 0, 5, 5, 0, 0], [0, 5, 5, 0, 0, 0, 0, 0, 0, 0, 0, 5, 5, 0, 0], [3, 0, 0, 4, 0, 0, 0, 0, 0, 0, 3, 0, 0, 4, 0], [0, 0, 0, 0, 0, 5, 5, 0, 0, 0, 0, 0, 0, 0, 0], [0, 0, 0, 0, 0, 5, 5, 0, 0, 0, 0, 1, 0, 0, 2], [0, 0, 0, 0, 3, 0, 0, 4, 0, 0, 0, 0, 5, 5, 0], [0, 0, 0, 0, 0, 0, 0, 0, 0, 0, 0, 0, 5, 5, 0], [0, 0, 0, 0, 0, 0, 0, 0, 0, 0, 0, 3, 0, 0, 4], [0, 1, 0, 0, 2, 0, 0, 0, 0, 0, 0, 0, 0, 0, 0], [0, 0, 5, 5, 0, 0, 0, 0, 1, 0, 0, 2, 0, 0, 0], [0, 0, 5, 5, 0, 0, 0, 0, 0, 5, 5, 0, 0, 0, 0], [0, 3, 0, 0, 4, 0, 0, 0, 0, 5, 5, 0, 0, 0, 0], [0, 0, 0, 0, 0, 0, 0, 0, 3, 0, 0, 4, 0, 0, 0], [0, 0, 0, 0, 0, 0, 0, 0, 0, 0, 0, 0, 0, 0, 0]], [[0, 0, 0, 2, 0, 0, 0, 0, 0, 0, 1, 0, 0, 2, 0], [0, 5, 5, 0, 0, 0, 0, 0, 0, 0, 0, 5, 5, 0, 0], [0, 5, 5, 0, 0, 0, 0, 0, 0, 0, 0, 5, 5, 0, 0], [3, 0, 0, 4, 0, 0, 0, 0, 0, 0, 3, 0, 0, 4, 0], [0, 0, 0, 0, 0, 5, 5, 0, 0, 0, 0, 0, 0, 0, 0], [0, 0, 0, 0, 0, 5, 5, 0, 0, 0, 0, 1, 0, 0, 2], [0, 0, 0, 0, 3, 0, 0, 4, 0, 0, 0, 0, 5, 5, 0], [0, 0, 0, 0, 0, 0, 0, 0, 0, 0, 0, 0, 5, 5, 0], [0, 0, 0, 0, 0, 0, 0, 0, 0, 0, 0, 3, 0, 0, 4], [0, 1, 0, 0, 2, 0, 0, 0, 0, 0, 0, 0, 0, 0, 0], [0, 0, 5, 5, 0, 0, 0, 0, 1, 0, 0, 2, 0, 0, 0], [0, 0, 5, 5, 0, 0, 0, 0, 0, 5, 5, 0, 0, 0, 0], [0, 3, 0, 0, 4, 0, 0, 0, 0, 5, 5, 0, 0, 0, 0], [0, 0, 0, 0, 0, 0, 0, 0, 3, 0, 0, 4, 0, 0, 0], [0, 0, 0, 0, 0, 0, 0, 0, 0, 0, 0, 0, 0, 0, 0]], [[1, 0, 0, 2, 0, 0, 0, 0, 0, 0, 1, 0, 0, 2, 0], [0, 5, 5, 0, 0, 0, 0, 0, 0, 0, 0, 5, 5, 0, 0], [0, 5, 5, 0, 0, 0, 0, 0, 0, 0, 0, 5, 5, 0, 0], [3, 0, 0, 4, 0, 0, 0, 0, 0, 0, 3, 0, 0, 4, 0], [0, 0, 0, 0, 0, 5, 5, 0, 0, 0, 0, 0, 0, 0, 0], [0, 0, 0, 0, 0, 5, 5, 0, 0, 0, 0, 1, 0, 0, 2], [0, 0, 0, 0, 3, 0, 0, 4, 0, 0, 0, 0, 5, 5, 0], [0, 0, 0, 0, 0, 0, 0, 0, 0, 0, 0, 0, 5, 5, 0], [0, 0, 0, 0, 0, 0, 0, 0, 0, 0, 0, 3, 0, 0, 4], [0, 1, 0, 0, 2, 0, 0, 0, 0, 0, 0, 0, 0, 0, 0], [0, 0, 5, 5, 0, 0, 0, 0, 1, 0, 0, 2, 0, 0, 0], [0, 0, 5, 5, 0, 0, 0, 0, 0, 5, 5, 0, 0, 0, 0], [0, 3, 0, 0, 4, 0, 0, 0, 0, 5, 5, 0, 0, 0, 0], [0, 0, 0, 0, 0, 0, 0, 0, 3, 0, 0, 4, 0, 0, 0], [0, 0, 0, 0, 0, 0, 0, 0, 0, 0, 0, 0, 0, 0, 0]], [[1, 0, 0, 2, 0, 0, 0, 0, 0, 0, 1, 0, 0, 2, 0], [0, 5, 5, 0, 0, 0, 0, 0, 0, 0, 0, 5, 5, 0, 0], [0, 5, 5, 0, 0, 0, 0, 0, 0, 0, 0, 5, 5, 0, 0], [3, 0, 0, 4, 1, 0, 0, 0, 0, 0, 3, 0, 0, 4, 0], [0, 0, 0, 0, 0, 5, 5, 0, 0, 0, 0, 0, 0, 0, 0], [0, 0, 0, 0, 0, 5, 5, 0, 0, 0, 0, 1, 0, 0, 2], [0, 0, 0, 0, 3, 0, 0, 4, 0, 0, 0, 0, 5, 5, 0], [0, 0, 0, 0, 0, 0, 0, 0, 0, 0, 0, 0, 5, 5, 0], [0, 0, 0, 0, 0, 0, 0, 0, 0, 0, 0, 3, 0, 0, 4], [0, 1, 0, 0, 2, 0, 0, 0, 0, 0, 0, 0, 0, 0, 0], [0, 0, 5, 5, 0, 0, 0, 0, 1, 0, 0, 2, 0, 0, 0], [0, 0, 5, 5, 0, 0, 0, 0, 0, 5, 5, 0, 0, 0, 0], [0, 3, 0, 0, 4, 0, 0, 0, 0, 5, 5, 0, 0, 0, 0], [0, 0, 0, 0, 0, 0, 0, 0, 3, 0, 0, 4, 0, 0, 0], [0, 0, 0, 0, 0, 0, 0, 0, 0, 0, 0, 0, 0, 0, 0]], [[1, 0, 0, 2, 0, 0, 0, 0, 0, 0, 1, 0, 0, 2, 0], [0, 5, 5, 0, 0, 0, 0, 0, 0, 0, 0, 5, 5, 0, 0], [0, 5, 5, 0, 0, 0, 0, 0, 0, 0, 0, 5, 5, 0, 0], [3, 0, 0, 4, 1, 0, 0, 0, 0, 0, 3, 0, 0, 4, 0], [0, 0, 0, 0, 0, 5, 5, 0, 0, 0, 0, 0, 0, 0, 0], [0, 0, 0, 0, 0, 5, 5, 0, 0, 0, 0, 1, 0, 0, 2], [0, 0, 0, 0, 3, 0, 0, 4, 0, 0, 0, 0, 5, 5, 0], [0, 0, 0, 0, 0, 0, 0, 0, 0, 0, 0, 0, 5, 5, 0], [0, 0, 0, 0, 0, 0, 0, 0, 0, 0, 0, 3, 0, 0, 4], [0, 1, 0, 0, 2, 0, 0, 0, 0, 0, 0, 0, 0, 0, 0], [0, 0, 5, 5, 0, 0, 0, 0, 1, 0, 0, 2, 0, 0, 0], [0, 0, 5, 5, 0, 0, 0, 0, 0, 5, 5, 0, 0, 0, 0], [0, 3, 0, 0, 4, 0, 0, 0, 0, 5, 5, 0, 0, 0, 0], [0, 0, 0, 0, 0, 0, 0, 0, 3, 0, 0, 4, 0, 0, 0], [0, 0, 0, 0, 0, 0, 0, 0, 0, 0, 0, 0, 0, 0, 0]], [[1, 0, 0, 2, 0, 0, 0, 0, 0, 0, 1, 0, 0, 2, 0], [0, 5, 5, 0, 0, 0, 0, 0, 0, 0, 0, 5, 5, 0, 0], [0, 5, 5, 0, 0, 0, 0, 0, 0, 0, 0, 5, 5, 0, 0], [3, 0, 0, 4, 1, 0, 0, 0, 0, 0, 3, 0, 0, 4, 0], [0, 0, 0, 0, 0, 5, 5, 0, 0, 0, 0, 0, 0, 0, 0], [0, 0, 0, 0, 0, 5, 5, 0, 0, 0, 0, 1, 0, 0, 2], [0, 0, 0, 0, 3, 0, 0, 4, 0, 0, 0, 0, 5, 5, 0], [0, 0, 0, 0, 0, 0, 0, 0, 0, 0, 0, 0, 5, 5, 0], [0, 0, 0, 0, 0, 0, 0, 0, 0, 0, 0, 3, 0, 0, 4], [0, 1, 0, 0, 2, 0, 0, 0, 0, 0, 0, 0, 0, 0, 0], [0, 0, 5, 5, 0, 0, 0, 0, 1, 0, 0, 2, 0, 0, 0], [0, 0, 5, 5, 0, 0, 0, 0, 0, 5, 5, 0, 0, 0, 0], [0, 3, 0, 0, 4, 0, 0, 0, 0, 5, 5, 0, 0, 0, 0], [0, 0, 0, 0, 0, 0, 0, 0, 3, 0, 0, 4, 0, 0, 0], [0, 0, 0, 0, 0, 0, 0, 0, 0, 0, 0, 0, 0, 0, 0]], [[1, 0, 0, 2, 0, 0, 0, 0, 0, 0, 1, 0, 0, 2, 0], [0, 5, 5, 0, 0, 0, 0, 0, 0, 0, 0, 5, 5, 0, 0], [0, 5, 5, 0, 0, 0, 0, 0, 0, 0, 0, 5, 5, 0, 0], [3, 0, 0, 4, 1, 0, 0, 2, 0, 0, 3, 0, 0, 4, 0], [0, 0, 0, 0, 0, 5, 5, 0, 0, 0, 0, 0, 0, 0, 0], [0, 0, 0, 0, 0, 5, 5, 0, 0, 0, 0, 1, 0, 0, 2], [0, 0, 0, 0, 3, 0, 0, 4, 0, 0, 0, 0, 5, 5, 0], [0, 0, 0, 0, 0, 0, 0, 0, 0, 0, 0, 0, 5, 5, 0], [0, 0, 0, 0, 0, 0, 0, 0, 0, 0, 0, 3, 0, 0, 4], [0, 1, 0, 0, 2, 0, 0, 0, 0, 0, 0, 0, 0, 0, 0], [0, 0, 5, 5, 0, 0, 0, 0, 1, 0, 0, 2, 0, 0, 0], [0, 0, 5, 5, 0, 0, 0, 0, 0, 5, 5, 0, 0, 0, 0], [0, 3, 0, 0, 4, 0, 0, 0, 0, 5, 5, 0, 0, 0, 0], [0, 0, 0, 0, 0, 0, 0, 0, 3, 0, 0, 4, 0, 0, 0], [0, 0, 0, 0, 0, 0, 0, 0, 0, 0, 0, 0, 0, 0, 0]], [[1, 0, 0, 2, 0, 0, 0, 0, 0, 0, 1, 0, 0, 2, 0], [0, 5, 5, 0, 0, 0, 0, 0, 0, 0, 0, 5, 5, 0, 0], [0, 5, 5, 0, 0, 0, 0, 0, 0, 0, 0, 5, 5, 0, 0], [3, 0, 0, 4, 1, 0, 0, 2, 0, 0, 3, 0, 0, 4, 0], [0, 0, 0, 0, 0, 5, 5, 0, 0, 0, 0, 0, 0, 0, 0], [0, 0, 0, 0, 0, 5, 5, 0, 0, 0, 0, 1, 0, 0, 2], [0, 0, 0, 0, 3, 0, 0, 4, 0, 0, 0, 0, 5, 5, 0], [0, 0, 0, 0, 0, 0, 0, 0, 0, 0, 0, 0, 5, 5, 0], [0, 0, 0, 0, 0, 0, 0, 0, 0, 0, 0, 3, 0, 0, 4], [0, 1, 0, 0, 2, 0, 0, 0, 0, 0, 0, 0, 0, 0, 0], [0, 0, 5, 5, 0, 0, 0, 0, 1, 0, 0, 2, 0, 0, 0], [0, 0, 5, 5, 0, 0, 0, 0, 0, 5, 5, 0, 0, 0, 0], [0, 3, 0, 0, 4, 0, 0, 0, 0, 5, 5, 0, 0, 0, 0], [0, 0, 0, 0, 0, 0, 0, 0, 3, 0, 0, 4, 0, 0, 0], [0, 0, 0, 0, 0, 0, 0, 0, 0, 0, 0, 0, 0, 0, 0]], [[1, 0, 0, 2, 0, 0, 0, 0, 0, 0, 1, 0, 0, 2, 0], [0, 5, 5, 0, 0, 0, 0, 0, 0, 0, 0, 5, 5, 0, 0], [0, 5, 5, 0, 0, 0, 0, 0, 0, 0, 0, 5, 5, 0, 0], [3, 0, 0, 4, 1, 0, 0, 2, 0, 0, 3, 0, 0, 4, 0], [0, 0, 0, 0, 0, 5, 5, 0, 0, 0, 0, 0, 0, 0, 0], [0, 0, 0, 0, 0, 5, 5, 0, 0, 0, 0, 1, 0, 0, 2], [0, 0, 0, 0, 3, 0, 0, 4, 0, 0, 0, 0, 5, 5, 0], [0, 0, 0, 0, 0, 0, 0, 0, 0, 0, 0, 0, 5, 5, 0], [0, 0, 0, 0, 0, 0, 0, 0, 0, 0, 0, 3, 0, 0, 4], [0, 1, 0, 0, 2, 0, 0, 0, 0, 0, 0, 0, 0, 0, 0], [0, 0, 5, 5, 0, 0, 0, 0, 1, 0, 0, 2, 0, 0, 0], [0, 0, 5, 5, 0, 0, 0, 0, 0, 5, 5, 0, 0, 0, 0], [0, 3, 0, 0, 4, 0, 0, 0, 0, 5, 5, 0, 0, 0, 0], [0, 0, 0, 0, 0, 0, 0, 0, 3, 0, 0, 4, 0, 0, 0], [0, 0, 0, 0, 0, 0, 0, 0, 0, 0, 0, 0, 0, 0, 0]], [[1, 0, 0, 2, 0, 0, 0, 0, 0, 0, 1, 0, 0, 2, 0], [0, 5, 5, 0, 0, 0, 0, 0, 0, 0, 0, 5, 5, 0, 0], [0, 5, 5, 0, 0, 0, 0, 0, 0, 0, 0, 5, 5, 0, 0], [3, 0, 0, 4, 1, 0, 0, 2, 0, 0, 3, 0, 0, 4, 0], [0, 0, 0, 0, 0, 5, 5, 0, 0, 0, 0, 0, 0, 0, 0], [0, 0, 0, 0, 0, 5, 5, 0, 0, 0, 0, 1, 0, 0, 2], [0, 0, 0, 0, 3, 0, 0, 4, 0, 0, 0, 0, 5, 5, 0], [0, 0, 0, 0, 0, 0, 0, 0, 0, 0, 0, 0, 5, 5, 0], [0, 0, 0, 0, 0, 0, 0, 0, 0, 0, 0, 3, 0, 0, 4], [0, 1, 0, 0, 2, 0, 0, 0, 0, 0, 0, 0, 0, 0, 0], [0, 0, 5, 5, 0, 0, 0, 0, 1, 0, 0, 2, 0, 0, 0], [0, 0, 5, 5, 0, 0, 0, 0, 0, 5, 5, 0, 0, 0, 0], [0, 3, 0, 0, 4, 0, 0, 0, 0, 5, 5, 0, 0, 0, 0], [0, 0, 0, 0, 0, 0, 0, 0, 3, 0, 0, 4, 0, 0, 0], [0, 0, 0, 0, 0, 0, 0, 0, 0, 0, 0, 0, 0, 0, 0]], [[1, 0, 0, 2, 0, 0, 0, 0, 0, 0, 1, 0, 0, 2, 0], [0, 5, 5, 0, 0, 0, 0, 0, 0, 0, 0, 5, 5, 0, 0], [0, 5, 5, 0, 0, 0, 0, 0, 0, 0, 0, 5, 5, 0, 0], [3, 0, 0, 4, 1, 0, 0, 2, 0, 0, 3, 0, 0, 4, 0], [0, 0, 0, 0, 0, 5, 5, 0, 0, 0, 0, 0, 0, 0, 0], [0, 0, 0, 0, 0, 5, 5, 0, 0, 0, 0, 1, 0, 0, 2], [0, 0, 0, 0, 3, 0, 0, 4, 0, 0, 0, 0, 5, 5, 0], [0, 0, 0, 0, 0, 0, 0, 0, 0, 0, 0, 0, 5, 5, 0], [0, 0, 0, 0, 0, 0, 0, 0, 0, 0, 0, 3, 0, 0, 4], [0, 1, 0, 0, 2, 0, 0, 0, 0, 0, 0, 0, 0, 0, 0], [0, 0, 5, 5, 0, 0, 0, 0, 1, 0, 0, 2, 0, 0, 0], [0, 0, 5, 5, 0, 0, 0, 0, 0, 5, 5, 0, 0, 0, 0], [0, 3, 0, 0, 4, 0, 0, 0, 0, 5, 5, 0, 0, 0, 0], [0, 0, 0, 0, 0, 0, 0, 0, 3, 0, 0, 4, 0, 0, 0], [0, 0, 0, 0, 0, 0, 0, 0, 0, 0, 0, 0, 0, 0, 0]], [[1, 0, 0, 2, 0, 0, 0, 0, 0, 0, 1, 0, 0, 2, 0], [0, 5, 5, 0, 0, 0, 0, 0, 0, 0, 0, 5, 5, 0, 0], [0, 5, 5, 0, 0, 0, 0, 0, 0, 0, 0, 5, 5, 0, 0], [3, 0, 0, 4, 1, 0, 0, 2, 0, 0, 3, 0, 0, 4, 0], [0, 0, 0, 0, 0, 5, 5, 0, 0, 0, 0, 0, 0, 0, 0], [0, 0, 0, 0, 0, 5, 5, 0, 0, 0, 0, 1, 0, 0, 2], [0, 0, 0, 0, 3, 0, 0, 4, 0, 0, 0, 0, 5, 5, 0], [0, 0, 0, 0, 0, 0, 0, 0, 0, 0, 0, 0, 5, 5, 0], [0, 0, 0, 0, 0, 0, 0, 0, 0, 0, 0, 3, 0, 0, 4], [0, 1, 0, 0, 2, 0, 0, 0, 0, 0, 0, 0, 0, 0, 0], [0, 0, 5, 5, 0, 0, 0, 0, 1, 0, 0, 2, 0, 0, 0], [0, 0, 5, 5, 0, 0, 0, 0, 0, 5, 5, 0, 0, 0, 0], [0, 3, 0, 0, 4, 0, 0, 0, 0, 5, 5, 0, 0, 0, 0], [0, 0, 0, 0, 0, 0, 0, 0, 3, 0, 0, 4, 0, 0, 0], [0, 0, 0, 0, 0, 0, 0, 0, 0, 0, 0, 0, 0, 0, 0]], [[1, 0, 0, 2, 0, 0, 0, 0, 0, 0, 1, 0, 0, 2, 0], [0, 5, 5, 0, 0, 0, 0, 0, 0, 0, 0, 5, 5, 0, 0], [0, 5, 5, 0, 0, 0, 0, 0, 0, 0, 0, 5, 5, 0, 0], [3, 0, 0, 4, 1, 0, 0, 2, 0, 0, 3, 0, 0, 4, 0], [0, 0, 0, 0, 0, 5, 5, 0, 0, 0, 0, 0, 0, 0, 0], [0, 0, 0, 0, 0, 5, 5, 0, 0, 0, 0, 1, 0, 0, 2], [0, 0, 0, 0, 3, 0, 0, 4, 0, 0, 0, 0, 5, 5, 0], [0, 0, 0, 0, 0, 0, 0, 0, 0, 0, 0, 0, 5, 5, 0], [0, 0, 0, 0, 0, 0, 0, 0, 0, 0, 0, 3, 0, 0, 4], [0, 1, 0, 0, 2, 0, 0, 0, 0, 0, 0, 0, 0, 0, 0], [0, 0, 5, 5, 0, 0, 0, 0, 1, 0, 0, 2, 0, 0, 0], [0, 0, 5, 5, 0, 0, 0, 0, 0, 5, 5, 0, 0, 0, 0], [0, 3, 0, 0, 4, 0, 0, 0, 0, 5, 5, 0, 0, 0, 0], [0, 0, 0, 0, 0, 0, 0, 0, 3, 0, 0, 4, 0, 0, 0], [0, 0, 0, 0, 0, 0, 0, 0, 0, 0, 0, 0, 0, 0, 0]], [[1, 0, 0, 2, 0, 0, 0, 0, 0, 0, 1, 0, 0, 2, 0], [0, 5, 5, 0, 0, 0, 0, 0, 0, 0, 0, 5, 5, 0, 0], [0, 5, 5, 0, 0, 0, 0, 0, 0, 0, 0, 5, 5, 0, 0], [3, 0, 0, 4, 1, 0, 0, 2, 0, 0, 3, 0, 0, 4, 0], [0, 0, 0, 0, 0, 5, 5, 0, 0, 0, 0, 0, 0, 0, 0], [0, 0, 0, 0, 0, 5, 5, 0, 0, 0, 0, 1, 0, 0, 2], [0, 0, 0, 0, 3, 0, 0, 4, 0, 0, 0, 0, 5, 5, 0], [0, 0, 0, 0, 0, 0, 0, 0, 0, 0, 0, 0, 5, 5, 0], [0, 0, 0, 0, 0, 0, 0, 0, 0, 0, 0, 3, 0, 0, 4], [0, 1, 0, 0, 2, 0, 0, 0, 0, 0, 0, 0, 0, 0, 0], [0, 0, 5, 5, 0, 0, 0, 0, 1, 0, 0, 2, 0, 0, 0], [0, 0, 5, 5, 0, 0, 0, 0, 0, 5, 5, 0, 0, 0, 0], [0, 3, 0, 0, 4, 0, 0, 0, 0, 5, 5, 0, 0, 0, 0], [0, 0, 0, 0, 0, 0, 0, 0, 3, 0, 0, 4, 0, 0, 0], [0, 0, 0, 0, 0, 0, 0, 0, 0, 0, 0, 0, 0, 0, 0]], [[1, 0, 0, 2, 0, 0, 0, 0, 0, 0, 1, 0, 0, 2, 0], [0, 5, 5, 0, 0, 0, 0, 0, 0, 0, 0, 5, 5, 0, 0], [0, 5, 5, 0, 0, 0, 0, 0, 0, 0, 0, 5, 5, 0, 0], [3, 0, 0, 4, 1, 0, 0, 2, 0, 0, 3, 0, 0, 4, 0], [0, 0, 0, 0, 0, 5, 5, 0, 0, 0, 0, 0, 0, 0, 0], [0, 0, 0, 0, 0, 5, 5, 0, 0, 0, 0, 1, 0, 0, 2], [0, 0, 0, 0, 3, 0, 0, 4, 0, 0, 0, 0, 5, 5, 0], [0, 0, 0, 0, 0, 0, 0, 0, 0, 0, 0, 0, 5, 5, 0], [0, 0, 0, 0, 0, 0, 0, 0, 0, 0, 0, 3, 0, 0, 4], [0, 1, 0, 0, 2, 0, 0, 0, 0, 0, 0, 0, 0, 0, 0], [0, 0, 5, 5, 0, 0, 0, 0, 1, 0, 0, 2, 0, 0, 0], [0, 0, 5, 5, 0, 0, 0, 0, 0, 5, 5, 0, 0, 0, 0], [0, 3, 0, 0, 4, 0, 0, 0, 0, 5, 5, 0, 0, 0, 0], [0, 0, 0, 0, 0, 0, 0, 0, 3, 0, 0, 4, 0, 0, 0], [0, 0, 0, 0, 0, 0, 0, 0, 0, 0, 0, 0, 0, 0, 0]], [[1, 0, 0, 2, 0, 0, 0, 0, 0, 0, 1, 0, 0, 2, 0], [0, 5, 5, 0, 0, 0, 0, 0, 0, 0, 0, 5, 5, 0, 0], [0, 5, 5, 0, 0, 0, 0, 0, 0, 0, 0, 5, 5, 0, 0], [3, 0, 0, 4, 1, 0, 0, 2, 0, 0, 3, 0, 0, 4, 0], [0, 0, 0, 0, 0, 5, 5, 0, 0, 0, 0, 0, 0, 0, 0], [0, 0, 0, 0, 0, 5, 5, 0, 0, 0, 0, 1, 0, 0, 2], [0, 0, 0, 0, 3, 0, 0, 4, 0, 0, 0, 0, 5, 5, 0], [0, 0, 0, 0, 0, 0, 0, 0, 0, 0, 0, 0, 5, 5, 0], [0, 0, 0, 0, 0, 0, 0, 0, 0, 0, 0, 3, 0, 0, 4], [0, 1, 0, 0, 2, 0, 0, 0, 0, 0, 0, 0, 0, 0, 0], [0, 0, 5, 5, 0, 0, 0, 0, 1, 0, 0, 2, 0, 0, 0], [0, 0, 5, 5, 0, 0, 0, 0, 0, 5, 5, 0, 0, 0, 0], [0, 3, 0, 0, 4, 0, 0, 0, 0, 5, 5, 0, 0, 0, 0], [0, 0, 0, 0, 0, 0, 0, 0, 3, 0, 0, 4, 0, 0, 0], [0, 0, 0, 0, 0, 0, 0, 0, 0, 0, 0, 0, 0, 0, 0]], [[1, 0, 0, 2, 0, 0, 0, 0, 0, 0, 1, 0, 0, 2, 0], [0, 5, 5, 0, 0, 0, 0, 0, 0, 0, 0, 5, 5, 0, 0], [0, 5, 5, 0, 0, 0, 0, 0, 0, 0, 0, 5, 5, 0, 0], [3, 0, 0, 4, 1, 0, 0, 2, 0, 0, 3, 0, 0, 4, 0], [0, 0, 0, 0, 0, 5, 5, 0, 0, 0, 0, 0, 0, 0, 0], [0, 0, 0, 0, 0, 5, 5, 0, 0, 0, 0, 1, 0, 0, 2], [0, 0, 0, 0, 3, 0, 0, 4, 0, 0, 0, 0, 5, 5, 0], [0, 0, 0, 0, 0, 0, 0, 0, 0, 0, 0, 0, 5, 5, 0], [0, 0, 0, 0, 0, 0, 0, 0, 0, 0, 0, 3, 0, 0, 4], [0, 1, 0, 0, 2, 0, 0, 0, 0, 0, 0, 0, 0, 0, 0], [0, 0, 5, 5, 0, 0, 0, 0, 1, 0, 0, 2, 0, 0, 0], [0, 0, 5, 5, 0, 0, 0, 0, 0, 5, 5, 0, 0, 0, 0], [0, 3, 0, 0, 4, 0, 0, 0, 0, 5, 5, 0, 0, 0, 0], [0, 0, 0, 0, 0, 0, 0, 0, 3, 0, 0, 4, 0, 0, 0], [0, 0, 0, 0, 0, 0, 0, 0, 0, 0, 0, 0, 0, 0, 0]], [[1, 0, 0, 2, 0, 0, 0, 0, 0, 0, 1, 0, 0, 2, 0], [0, 5, 5, 0, 0, 0, 0, 0, 0, 0, 0, 5, 5, 0, 0], [0, 5, 5, 0, 0, 0, 0, 0, 0, 0, 0, 5, 5, 0, 0], [3, 0, 0, 4, 1, 0, 0, 2, 0, 0, 3, 0, 0, 4, 0], [0, 0, 0, 0, 0, 5, 5, 0, 0, 0, 0, 0, 0, 0, 0], [0, 0, 0, 0, 0, 5, 5, 0, 0, 0, 0, 1, 0, 0, 2], [0, 0, 0, 0, 3, 0, 0, 4, 0, 0, 0, 0, 5, 5, 0], [0, 0, 0, 0, 0, 0, 0, 0, 0, 0, 0, 0, 5, 5, 0], [0, 0, 0, 0, 0, 0, 0, 0, 0, 0, 0, 3, 0, 0, 4], [0, 1, 0, 0, 2, 0, 0, 0, 0, 0, 0, 0, 0, 0, 0], [0, 0, 5, 5, 0, 0, 0, 0, 1, 0, 0, 2, 0, 0, 0], [0, 0, 5, 5, 0, 0, 0, 0, 0, 5, 5, 0, 0, 0, 0], [0, 3, 0, 0, 4, 0, 0, 0, 0, 5, 5, 0, 0, 0, 0], [0, 0, 0, 0, 0, 0, 0, 0, 3, 0, 0, 4, 0, 0, 0], [0, 0, 0, 0, 0, 0, 0, 0, 0, 0, 0, 0, 0, 0, 0]], [[1, 0, 0, 2, 0, 0, 0, 0, 0, 0, 1, 0, 0, 2, 0], [0, 5, 5, 0, 0, 0, 0, 0, 0, 0, 0, 5, 5, 0, 0], [0, 5, 5, 0, 0, 0, 0, 0, 0, 0, 0, 5, 5, 0, 0], [3, 0, 0, 4, 1, 0, 0, 2, 0, 0, 3, 0, 0, 4, 0], [0, 0, 0, 0, 0, 5, 5, 0, 0, 0, 0, 0, 0, 0, 0], [0, 0, 0, 0, 0, 5, 5, 0, 0, 0, 0, 1, 0, 0, 2], [0, 0, 0, 0, 3, 0, 0, 4, 0, 0, 0, 0, 5, 5, 0], [0, 0, 0, 0, 0, 0, 0, 0, 0, 0, 0, 0, 5, 5, 0], [0, 0, 0, 0, 0, 0, 0, 0, 0, 0, 0, 3, 0, 0, 4], [0, 1, 0, 0, 2, 0, 0, 0, 0, 0, 0, 0, 0, 0, 0], [0, 0, 5, 5, 0, 0, 0, 0, 1, 0, 0, 2, 0, 0, 0], [0, 0, 5, 5, 0, 0, 0, 0, 0, 5, 5, 0, 0, 0, 0], [0, 3, 0, 0, 4, 0, 0, 0, 0, 5, 5, 0, 0, 0, 0], [0, 0, 0, 0, 0, 0, 0, 0, 3, 0, 0, 4, 0, 0, 0], [0, 0, 0, 0, 0, 0, 0, 0, 0, 0, 0, 0, 0, 0, 0]], [[1, 0, 0, 2, 0, 0, 0, 0, 0, 0, 1, 0, 0, 2, 0], [0, 5, 5, 0, 0, 0, 0, 0, 0, 0, 0, 5, 5, 0, 0], [0, 5, 5, 0, 0, 0, 0, 0, 0, 0, 0, 5, 5, 0, 0], [3, 0, 0, 4, 1, 0, 0, 2, 0, 0, 3, 0, 0, 4, 0], [0, 0, 0, 0, 0, 5, 5, 0, 0, 0, 0, 0, 0, 0, 0], [0, 0, 0, 0, 0, 5, 5, 0, 0, 0, 0, 1, 0, 0, 2], [0, 0, 0, 0, 3, 0, 0, 4, 0, 0, 0, 0, 5, 5, 0], [0, 0, 0, 0, 0, 0, 0, 0, 0, 0, 0, 0, 5, 5, 0], [0, 0, 0, 0, 0, 0, 0, 0, 0, 0, 0, 3, 0, 0, 4], [0, 1, 0, 0, 2, 0, 0, 0, 0, 0, 0, 0, 0, 0, 0], [0, 0, 5, 5, 0, 0, 0, 0, 1, 0, 0, 2, 0, 0, 0], [0, 0, 5, 5, 0, 0, 0, 0, 0, 5, 5, 0, 0, 0, 0], [0, 3, 0, 0, 4, 0, 0, 0, 0, 5, 5, 0, 0, 0, 0], [0, 0, 0, 0, 0, 0, 0, 0, 3, 0, 0, 4, 0, 0, 0], [0, 0, 0, 0, 0, 0, 0, 0, 0, 0, 0, 0, 0, 0, 0]]], "target": [[[1, 0, 0, 2, 0, 0, 0, 0, 0, 0, 1, 0, 0, 2, 0], [0, 5, 5, 0, 0, 0, 0, 0, 0, 0, 0, 5, 5, 0, 0], [0, 5, 5, 0, 0, 0, 0, 0, 0, 0, 0, 5, 5, 0, 0], [3, 0, 0, 4, 1, 0, 0, 2, 0, 0, 3, 0, 0, 4, 0], [0, 0, 0, 0, 0, 5, 5, 0, 0, 0, 0, 0, 0, 0, 0], [0, 0, 0, 0, 0, 5, 5, 0, 0, 0, 0, 1, 0, 0, 2], [0, 0, 0, 0, 3, 0, 0, 4, 0, 0, 0, 0, 5, 5, 0], [0, 0, 0, 0, 0, 0, 0, 0, 0, 0, 0, 0, 5, 5, 0], [0, 0, 0, 0, 0, 0, 0, 0, 0, 0, 0, 3, 0, 0, 4], [0, 1, 0, 0, 2, 0, 0, 0, 0, 0, 0, 0, 0, 0, 0], [0, 0, 5, 5, 0, 0, 0, 0, 1, 0, 0, 2, 0, 0, 0], [0, 0, 5, 5, 0, 0, 0, 0, 0, 5, 5, 0, 0, 0, 0], [0, 3, 0, 0, 4, 0, 0, 0, 0, 5, 5, 0, 0, 0, 0], [0, 0, 0, 0, 0, 0, 0, 0, 3, 0, 0, 4, 0, 0, 0], [0, 0, 0, 0, 0, 0, 0, 0, 0, 0, 0, 0, 0, 0, 0]]]}}