{"task_id": "fc754716", "status": "ok", "reason": null, "nca_version": "v2", "best_train_acc": 100.0, "config": {"epochs": 2000, "steps": 32, "lr": 0.001, "hidden": 32, "context_ch": 16, "attn_dim": 32, "timeout_s": 120.0}, "best_loss": 0.012482, "pairs": [{"pair": 0, "input": [[0, 0, 0, 0, 0, 0, 0], [0, 0, 0, 0, 0, 0, 0], [0, 0, 0, 1, 0, 0, 0], [0, 0, 0, 0, 0, 0, 0], [0, 0, 0, 0, 0, 0, 0]], "target": [[1, 1, 1, 1, 1, 1, 1], [1, 0, 0, 0, 0, 0, 1], [1, 0, 0, 0, 0, 0, 1], [1, 0, 0, 0, 0, 0, 1], [1, 1, 1, 1, 1, 1, 1]], "steps": [[[0, 0, 0, 0, 0, 0, 0], [0, 0, 0, 0, 0, 0, 0], [0, 0, 0, 1, 0, 0, 0], [0, 0, 0, 0, 0, 0, 0], [0, 0, 0, 0, 0, 0, 0]], [[0, 1, 0, 0, 0, 0, 0], [0, 0, 0, 0, 0, 0, 0], [1, 0, 0, 1, 0, 0, 0], [0, 0, 0, 0, 0, 0, 0], [0, 0, 0, 1, 0, 1, 0]], [[1, 1, 1, 0, 1, 0, 1], [0, 0, 0, 0, 0, 0, 1], [1, 0, 0, 0, 0, 0, 0], [1, 0, 0, 0, 0, 0, 0], [0, 1, 0, 1, 0, 1, 0]], [[1, 1, 1, 0, 1, 0, 1], [1, 0, 0, 0, 0, 0, 1], [1, 0, 0, 0, 0, 0, 1], [1, 0, 0, 0, 0, 0, 0], [0, 1, 0, 1, 1, 1, 1]], [[1, 1, 1, 0, 1, 1, 1], [1, 0, 0, 0, 0, 0, 1], [1, 0, 0, 0, 0, 0, 1], [1, 0, 0, 0, 0, 0, 1], [1, 1, 1, 1, 1, 1, 1]], [[1, 1, 1, 1, 1, 1, 1], [1, 0, 0, 0, 0, 0, 1], [1, 0, 0, 0, 0, 0, 1], [1, 0, 0, 0, 0, 0, 1], [1, 1, 1, 1, 1, 1, 1]], [[1, 1, 1, 1, 1, 1, 1], [1, 0, 0, 0, 0, 0, 1], [1, 0, 0, 0, 0, 0, 1], [1, 0, 0, 0, 0, 0, 1], [1, 1, 1, 1, 1, 1, 1]], [[1, 1, 1, 1, 1, 1, 1], [1, 0, 0, 0, 0, 0, 1], [1, 0, 0, 0, 0, 0, 1], [1, 0, 0, 0, 0, 0, 1], [1, 1, 1, 1, 1, 1, 1]], [[1, 1, 1, 1, 1, 1, 1], [1, 0, 0, 0, 0, 0, 1], [1, 0, 0, 0, 0, 0, 1], [1, 0, 0, 0, 0, 0, 1], [1, 1, 1, 1, 1, 1, 1]], [[1, 1, 1, 1, 1, 1, 1], [1, 0, 0, 0, 0, 0, 1], [1, 0, 0, 0, 0, 0, 1], [1, 0, 0, 0, 0, 0, 1], [1, 1, 1, 1, 1, 1, 1]], [[1, 1, 1, 1, 1, 1, 1], [1, 0, 0, 0, 0, 0, 1], [1, 0, 0, 0, 0, 0, 1], [1, 0, 0, 0, 0, 0, 1], [1, 1, 1, 1, 1, 1, 1]], [[1, 1, 1, 1, 1, 1, 1], [1, 0, 0, 0, 0, 0, 1], [1, 0, 0, 0, 0, 0, 1], [1, 0, 0, 0, 0, 0, 1], [1, 1, 1, 1, 1, 1, 1]], [[1, 1, 1, 1, 1, 1, 1], [1, 0, 0, 0, 0, 0, 1], [1, 0, 0, 0, 0, 0, 1], [1, 0, 0, 0, 0, 0, 1], [1, 1, 1, 1, 1, 1, 1]], [[1, 1, 1, 1, 1, 1, 1], [1, 0, 0, 0, 0, 0, 1], [1, 0, 0, 0, 0, 0, 1], [1, 0, 0, 0, 0, 0, 1], [1, 1, 1, 1, 1, 1, 1]], [[1, 1, 1, 1, 1, 1, 1], [1, 0, 0, 0, 0, 0, 1], [1, 0, 0, 0, 0, 0, 1], [1, 0, 0, 0, 0, 0, 1], [1, 1, 1, 1, 1, 1, 1]], [[1, 1, 1, 1, 1, 1, 1], [1, 0, 0, 0, 0, 0, 1], [1, 0, 0, 0, 0, 0, 1], [1, 0, 0, 0, 0, 0, 1], [1, 1, 1, 1, 1, 1, 1]], [[1, 1, 1, 1, 1, 1, 1], [1, 0, 0, 0, 0, 0, 1], [1, 0, 0, 0, 0, 0, 1], [1, 0, 0, 0, 0, 0, 1], [1, 1, 1, 1, 1, 1, 1]], [[1, 1, 1, 1, 1, 1, 1], [1, 0, 0, 0, 0, 0, 1], [1, 0, 0, 0, 0, 0, 1], [1, 0, 0, 0, 0, 0, 1], [1, 1, 1, 1, 1, 1, 1]], [[1, 1, 1, 1, 1, 1, 1], [1, 0, 0, 0, 0, 0, 1], [1, 0, 0, 0, 0, 0, 1], [1, 0, 0, 0, 0, 0, 1], [1, 1, 1, 1, 1, 1, 1]], [[1, 1, 1, 1, 1, 1, 1], [1, 0, 0, 0, 0, 0, 1], [1, 0, 0, 0, 0, 0, 1], [1, 0, 0, 0, 0, 0, 1], [1, 1, 1, 1, 1, 1, 1]], [[1, 1, 1, 1, 1, 1, 1], [1, 0, 0, 0, 0, 0, 1], [1, 0, 0, 0, 0, 0, 1], [1, 0, 0, 0, 0, 0, 1], [1, 1, 1, 1, 1, 1, 1]], [[1, 1, 1, 1, 1, 1, 1], [1, 0, 0, 0, 0, 0, 1], [1, 0, 0, 0, 0, 0, 1], [1, 0, 0, 0, 0, 0, 1], [1, 1, 1, 1, 1, 1, 1]], [[1, 1, 1, 1, 1, 1, 1], [1, 0, 0, 0, 0, 0, 1], [1, 0, 0, 0, 0, 0, 1], [1, 0, 0, 0, 0, 0, 1], [1, 1, 1, 1, 1, 1, 1]], [[1, 1, 1, 1, 1, 1, 1], [1, 0, 0, 0, 0, 0, 1], [1, 0, 0, 0, 0, 0, 1], [1, 0, 0, 0, 0, 0, 1], [1, 1, 1, 1, 1, 1, 1]], [[1, 1, 1, 1, 1, 1, 1], [1, 0, 0, 0, 0, 0, 1], [1, 0, 0, 0, 0, 0, 1], [1, 0, 0, 0, 0, 0, 1], [1, 1, 1, 1, 1, 1, 1]], [[1, 1, 1, 1, 1, 1, 1], [1, 0, 0, 0, 0, 0, 1], [1, 0, 0, 0, 0, 0, 1], [1, 0, 0, 0, 0, 0, 1], [1, 1, 1, 1, 1, 1, 1]], [[1, 1, 1, 1, 1, 1, 1], [1, 0, 0, 0, 0, 0, 1], [1, 0, 0, 0, 0, 0, 1], [1, 0, 0, 0, 0, 0, 1], [1, 1, 1, 1, 1, 1, 1]], [[1, 1, 1, 1, 1, 1, 1], [1, 0, 0, 0, 0, 0, 1], [1, 0, 0, 0, 0, 0, 1], [1, 0, 0, 0, 0, 0, 1], [1, 1, 1, 1, 1, 1, 1]], [[1, 1, 1, 1, 1, 1, 1], [1, 0, 0, 0, 0, 0, 1], [1, 0, 0, 0, 0, 0, 1], [1, 0, 0, 0, 0, 0, 1], [1, 1, 1, 1, 1, 1, 1]], [[1, 1, 1, 1, 1, 1, 1], [1, 0, 0, 0, 0, 0, 1], [1, 0, 0, 0, 0, 0, 1], [1, 0, 0, 0, 0, 0, 1], [1, 1, 1, 1, 1, 1, 1]], [[1, 1, 1, 1, 1, 1, 1], [1, 0, 0, 0, 0, 0, 1], [1, 0, 0, 0, 0, 0, 1], [1, 0, 0, 0, 0, 0, 1], [1, 1, 1, 1, 1, 1, 1]], [[1, 1, 1, 1, 1, 1, 1], [1, 0, 0, 0, 0, 0, 1], [1, 0, 0, 0, 0, 0, 1], [1, 0, 0, 0, 0, 0, 1], [1, 1, 1, 1, 1, 1, 1]], [[1, 1, 1, 1, 1, 1, 1], [1, 0, 0, 0, 0, 0, 1], [1, 0, 0, 0, 0, 0, 1], [1, 0, 0, 0, 0, 0, 1], [1, 1, 1, 1, 1, 1, 1]]], "accs": [40.0, 51.43, 74.29, 85.71, 97.14, 100.0, 100.0, 100.0, 100.0, 100.0, 100.0, 100.0, 100.0, 100.0, 100.0, 100.0, 100.0, 100.0, 100.0, 100.0, 100.0, 100.0, 100.0, 100.0, 100.0, 100.0, 100.0, 100.0, 100.0, 100.0, 100.0, 100.0, 100.0], "exact": true}, {"pair": 1, "input": [[0, 0, 0], [0, 0, 0], [0, 3, 0], [0, 0, 0], [0, 0, 0]], "target": [[3, 3, 3], [3, 0, 3], [3, 0, 3], [3, 0, 3], [3, 3, 3]], "steps": [[[0, 0, 0], [0, 0, 0], [0, 3, 0], [0, 0, 0], [0, 0, 0]], [[0, 0, 3], [0, 0, 3], [3, 0, 3], [0, 0, 3], [0, 0, 3]], [[0, 3, 3], [3, 0, 3], [3, 0, 3], [0, 0, 3], [0, 3, 3]], [[3, 3, 3], [3, 0, 3], [3, 0, 3], [0, 0, 3], [0, 3, 3]], [[3, 3, 3], [3, 0, 3], [3, 0, 3], [3, 0, 3], [3, 3, 3]], [[3, 3, 3], [3, 0, 3], [3, 0, 3], [3, 0, 3], [3, 3, 3]], [[3, 3, 3], [3, 0, 3], [3, 0, 3], [3, 0, 3], [3, 3, 3]], [[3, 3, 3], [3, 0, 3], [3, 0, 3], [3, 0, 3], [3, 3, 3]], [[3, 3, 3], [3, 0, 3], [3, 0, 3], [3, 0, 3], [3, 3, 3]], [[3, 3, 3], [3, 0, 3], [3, 0, 3], [3, 0, 3], [3, 3, 3]], [[3, 3, 3], [3, 0, 3], [3, 0, 3], [3, 0, 3], [3, 3, 3]], [[3, 3, 3], [3, 0, 3], [3, 0, 3], [3, 0, 3], [3, 3, 3]], [[3, 3, 3], [3, 0, 3], [3, 0, 3], [3, 0, 3], [3, 3, 3]], [[3, 3, 3], [3, 0, 3], [3, 0, 3], [3, 0, 3], [3, 3, 3]], [[3, 3, 3], [3, 0, 3], [3, 0, 3], [3, 0, 3], [3, 3, 3]], [[3, 3, 3], [3, 0, 3], [3, 0, 3], [3, 0, 3], [3, 3, 3]], [[3, 3, 3], [3, 0, 3], [3, 0, 3], [3, 0, 3], [3, 3, 3]], [[3, 3, 3], [3, 0, 3], [3, 0, 3], [3, 0, 3], [3, 3, 3]], [[3, 3, 3], [3, 0, 3], [3, 0, 3], [3, 0, 3], [3, 3, 3]], [[3, 3, 3], [3, 0, 3], [3, 0, 3], [3, 0, 3], [3, 3, 3]], [[3, 3, 3], [3, 0, 3], [3, 0, 3], [3, 0, 3], [3, 3, 3]], [[3, 3, 3], [3, 0, 3], [3, 0, 3], [3, 0, 3], [3, 3, 3]], [[3, 3, 3], [3, 0, 3], [3, 0, 3], [3, 0, 3], [3, 3, 3]], [[3, 3, 3], [3, 0, 3], [3, 0, 3], [3, 0, 3], [3, 3, 3]], [[3, 3, 3], [3, 0, 3], [3, 0, 3], [3, 0, 3], [3, 3, 3]], [[3, 3, 3], [3, 0, 3], [3, 0, 3], [3, 0, 3], [3, 3, 3]], [[3, 3, 3], [3, 0, 3], [3, 0, 3], [3, 0, 3], [3, 3, 3]], [[3, 3, 3], [3, 0, 3], [3, 0, 3], [3, 0, 3], [3, 3, 3]], [[3, 3, 3], [3, 0, 3], [3, 0, 3], [3, 0, 3], [3, 3, 3]], [[3, 3, 3], [3, 0, 3], [3, 0, 3], [3, 0, 3], [3, 3, 3]], [[3, 3, 3], [3, 0, 3], [3, 0, 3], [3, 0, 3], [3, 3, 3]], [[3, 3, 3], [3, 0, 3], [3, 0, 3], [3, 0, 3], [3, 3, 3]], [[3, 3, 3], [3, 0, 3], [3, 0, 3], [3, 0, 3], [3, 3, 3]]], "accs": [13.33, 60.0, 80.0, 86.67, 100.0, 100.0, 100.0, 100.0, 100.0, 100.0, 100.0, 100.0, 100.0, 100.0, 100.0, 100.0, 100.0, 100.0, 100.0, 100.0, 100.0, 100.0, 100.0, 100.0, 100.0, 100.0, 100.0, 100.0, 100.0, 100.0, 100.0, 100.0, 100.0], "exact": true}, {"pair": 2, "input": [[0, 0, 0, 0, 0], [0, 0, 0, 0, 0], [0, 0, 6, 0, 0], [0, 0, 0, 0, 0], [0, 0, 0, 0, 0]], "target": [[6, 6, 6, 6, 6], [6, 0, 0, 0, 6], [6, 0, 0, 0, 6], [6, 0, 0, 0, 6], [6, 6, 6, 6, 6]], "steps": [[[0, 0, 0, 0, 0], [0, 0, 0, 0, 0], [0, 0, 6, 0, 0], [0, 0, 0, 0, 0], [0, 0, 0, 0, 0]], [[0, 6, 6, 0, 6], [0, 0, 0, 0, 0], [6, 0, 6, 0, 6], [6, 0, 0, 0, 0], [6, 0, 0, 6, 0]], [[0, 6, 6, 6, 6], [6, 0, 0, 0, 6], [6, 0, 6, 0, 6], [6, 0, 0, 0, 6], [6, 6, 6, 6, 6]], [[6, 6, 6, 6, 6], [6, 0, 0, 0, 6], [6, 0, 6, 0, 6], [6, 0, 0, 0, 6], [6, 6, 6, 6, 6]], [[6, 6, 6, 6, 6], [6, 0, 0, 0, 6], [6, 0, 0, 0, 6], [6, 0, 0, 0, 6], [6, 6, 6, 6, 6]], [[6, 6, 6, 6, 6], [6, 0, 0, 0, 6], [6, 0, 0, 0, 6], [6, 0, 0, 0, 6], [6, 6, 6, 6, 6]], [[6, 6, 6, 6, 6], [6, 0, 0, 0, 6], [6, 0, 0, 0, 6], [6, 0, 0, 0, 6], [6, 6, 6, 6, 6]], [[6, 6, 6, 6, 6], [6, 0, 0, 0, 6], [6, 0, 0, 0, 6], [6, 0, 0, 0, 6], [6, 6, 6, 6, 6]], [[6, 6, 6, 6, 6], [6, 0, 0, 0, 6], [6, 0, 0, 0, 6], [6, 0, 0, 0, 6], [6, 6, 6, 6, 6]], [[6, 6, 6, 6, 6], [6, 0, 0, 0, 6], [6, 0, 0, 0, 6], [6, 0, 0, 0, 6], [6, 6, 6, 6, 6]], [[6, 6, 6, 6, 6], [6, 0, 0, 0, 6], [6, 0, 0, 0, 6], [6, 0, 0, 0, 6], [6, 6, 6, 6, 6]], [[6, 6, 6, 6, 6], [6, 0, 0, 0, 6], [6, 0, 0, 0, 6], [6, 0, 0, 0, 6], [6, 6, 6, 6, 6]], [[6, 6, 6, 6, 6], [6, 0, 0, 0, 6], [6, 0, 0, 0, 6], [6, 0, 0, 0, 6], [6, 6, 6, 6, 6]], [[6, 6, 6, 6, 6], [6, 0, 0, 0, 6], [6, 0, 0, 0, 6], [6, 0, 0, 0, 6], [6, 6, 6, 6, 6]], [[6, 6, 6, 6, 6], [6, 0, 0, 0, 6], [6, 0, 0, 0, 6], [6, 0, 0, 0, 6], [6, 6, 6, 6, 6]], [[6, 6, 6, 6, 6], [6, 0, 0, 0, 6], [6, 0, 0, 0, 6], [6, 0, 0, 0, 6], [6, 6, 6, 6, 6]], [[6, 6, 6, 6, 6], [6, 0, 0, 0, 6], [6, 0, 0, 0, 6], [6, 0, 0, 0, 6], [6, 6, 6, 6, 6]], [[6, 6, 6, 6, 6], [6, 0, 0, 0, 6], [6, 0, 0, 0, 6], [6, 0, 0, 0, 6], [6, 6, 6, 6, 6]], [[6, 6, 6, 6, 6], [6, 0, 0, 0, 6], [6, 0, 0, 0, 6], [6, 0, 0, 0, 6], [6, 6, 6, 6, 6]], [[6, 6, 6, 6, 6], [6, 0, 0, 0, 6], [6, 0, 0, 0, 6], [6, 0, 0, 0, 6], [6, 6, 6, 6, 6]], [[6, 6, 6, 6, 6], [6, 0, 0, 0, 6], [6, 0, 0, 0, 6], [6, 0, 0, 0, 6], [6, 6, 6, 6, 6]], [[6, 6, 6, 6, 6], [6, 0, 0, 0, 6], [6, 0, 0, 0, 6], [6, 0, 0, 0, 6], [6, 6, 6, 6, 6]], [[6, 6, 6, 6, 6], [6, 0, 0, 0, 6], [6, 0, 0, 0, 6], [6, 0, 0, 0, 6], [6, 6, 6, 6, 6]], [[6, 6, 6, 6, 6], [6, 0, 0, 0, 6], [6, 0, 0, 0, 6], [6, 0, 0, 0, 6], [6, 6, 6, 6, 6]], [[6, 6, 6, 6, 6], [6, 0, 0, 0, 6], [6, 0, 0, 0, 6], [6, 0, 0, 0, 6], [6, 6, 6, 6, 6]], [[6, 6, 6, 6, 6], [6, 0, 0, 0, 6], [6, 0, 0, 0, 6], [6, 0, 0, 0, 6], [6, 6, 6, 6, 6]], [[6, 6, 6, 6, 6], [6, 0, 0, 0, 6], [6, 0, 0, 0, 6], [6, 0, 0, 0, 6], [6, 6, 6, 6, 6]], [[6, 6, 6, 6, 6], [6, 0, 0, 0, 6], [6, 0, 0, 0, 6], [6, 0, 0, 0, 6], [6, 6, 6, 6, 6]], [[6, 6, 6, 6, 6], [6, 0, 0, 0, 6], [6, 0, 0, 0, 6], [6, 0, 0, 0, 6], [6, 6, 6, 6, 6]], [[6, 6, 6, 6, 6], [6, 0, 0, 0, 6], [6, 0, 0, 0, 6], [6, 0, 0, 0, 6], [6, 6, 6, 6, 6]], [[6, 6, 6, 6, 6], [6, 0, 0, 0, 6], [6, 0, 0, 0, 6], [6, 0, 0, 0, 6], [6, 6, 6, 6, 6]], [[6, 6, 6, 6, 6], [6, 0, 0, 0, 6], [6, 0, 0, 0, 6], [6, 0, 0, 0, 6], [6, 6, 6, 6, 6]], [[6, 6, 6, 6, 6], [6, 0, 0, 0, 6], [6, 0, 0, 0, 6], [6, 0, 0, 0, 6], [6, 6, 6, 6, 6]]], "accs": [32.0, 64.0, 92.0, 96.0, 100.0, 100.0, 100.0, 100.0, 100.0, 100.0, 100.0, 100.0, 100.0, 100.0, 100.0, 100.0, 100.0, 100.0, 100.0, 100.0, 100.0, 100.0, 100.0, 100.0, 100.0, 100.0, 100.0, 100.0, 100.0, 100.0, 100.0, 100.0, 100.0], "exact": true}, {"pair": 3, "input": [[0, 0, 0], [0, 2, 0], [0, 0, 0]], "target": [[2, 2, 2], [2, 0, 2], [2, 2, 2]], "steps": [[[0, 0, 0], [0, 2, 0], [0, 0, 0]], [[2, 0, 2], [0, 0, 0], [0, 2, 0]], [[2, 0, 2], [0, 0, 2], [0, 2, 2]], [[2, 2, 2], [2, 0, 2], [0, 2, 2]], [[2, 2, 2], [2, 0, 2], [2, 2, 2]], [[2, 2, 2], [2, 0, 2], [2, 2, 2]], [[2, 2, 2], [2, 0, 2], [2, 2, 2]], [[2, 2, 2], [2, 0, 2], [2, 2, 2]], [[2, 2, 2], [2, 0, 2], [2, 2, 2]], [[2, 2, 2], [2, 0, 2], [2, 2, 2]], [[2, 2, 2], [2, 0, 2], [2, 2, 2]], [[2, 2, 2], [2, 0, 2], [2, 2, 2]], [[2, 2, 2], [2, 0, 2], [2, 2, 2]], [[2, 2, 2], [2, 0, 2], [2, 2, 2]], [[2, 2, 2], [2, 0, 2], [2, 2, 2]], [[2, 2, 2], [2, 0, 2], [2, 2, 2]], [[2, 2, 2], [2, 0, 2], [2, 2, 2]], [[2, 2, 2], [2, 0, 2], [2, 2, 2]], [[2, 2, 2], [2, 0, 2], [2, 2, 2]], [[2, 2, 2], [2, 0, 2], [2, 2, 2]], [[2, 2, 2], [2, 0, 2], [2, 2, 2]], [[2, 2, 2], [2, 0, 2], [2, 2, 2]], [[2, 2, 2], [2, 0, 2], [2, 2, 2]], [[2, 2, 2], [2, 0, 2], [2, 2, 2]], [[2, 2, 2], [2, 0, 2], [2, 2, 2]], [[2, 2, 2], [2, 0, 2], [2, 2, 2]], [[2, 2, 2], [2, 0, 2], [2, 2, 2]], [[2, 2, 2], [2, 0, 2], [2, 2, 2]], [[2, 2, 2], [2, 0, 2], [2, 2, 2]], [[2, 2, 2], [2, 0, 2], [2, 2, 2]], [[2, 2, 2], [2, 0, 2], [2, 2, 2]], [[2, 2, 2], [2, 0, 2], [2, 2, 2]], [[2, 2, 2], [2, 0, 2], [2, 2, 2]]], "accs": [0.0, 44.44, 66.67, 88.89, 100.0, 100.0, 100.0, 100.0, 100.0, 100.0, 100.0, 100.0, 100.0, 100.0, 100.0, 100.0, 100.0, 100.0, 100.0, 100.0, 100.0, 100.0, 100.0, 100.0, 100.0, 100.0, 100.0, 100.0, 100.0, 100.0, 100.0, 100.0, 100.0], "exact": true}], "test": {"input": [[0, 0, 0, 0, 0, 0, 0], [0, 0, 0, 0, 0, 0, 0], [0, 0, 0, 0, 0, 0, 0], [0, 0, 0, 0, 0, 0, 0], [0, 0, 0, 8, 0, 0, 0], [0, 0, 0, 0, 0, 0, 0], [0, 0, 0, 0, 0, 0, 0], [0, 0, 0, 0, 0, 0, 0], [0, 0, 0, 0, 0, 0, 0]], "steps": [[[0, 0, 0, 0, 0, 0, 0], [0, 0, 0, 0, 0, 0, 0], [0, 0, 0, 0, 0, 0, 0], [0, 0, 0, 0, 0, 0, 0], [0, 0, 0, 8, 0, 0, 0], [0, 0, 0, 0, 0, 0, 0], [0, 0, 0, 0, 0, 0, 0], [0, 0, 0, 0, 0, 0, 0], [0, 0, 0, 0, 0, 0, 0]], [[0, 8, 8, 8, 0, 0, 0], [8, 0, 0, 0, 0, 0, 8], [8, 0, 0, 0, 0, 0, 0], [0, 0, 0, 0, 0, 0, 8], [8, 0, 0, 8, 0, 0, 8], [8, 0, 0, 0, 0, 0, 0], [0, 0, 0, 0, 0, 0, 8], [0, 0, 0, 0, 0, 0, 8], [0, 0, 8, 8, 0, 0, 8]], [[0, 8, 8, 8, 0, 8, 8], [8, 0, 0, 0, 0, 0, 8], [8, 0, 8, 0, 0, 0, 0], [8, 0, 0, 0, 0, 0, 8], [8, 0, 0, 0, 0, 0, 8], [8, 0, 0, 0, 0, 0, 0], [0, 0, 0, 0, 0, 0, 8], [8, 0, 0, 0, 0, 0, 8], [8, 0, 8, 8, 8, 0, 8]], [[0, 8, 8, 8, 0, 8, 8], [8, 0, 0, 0, 0, 0, 8], [8, 0, 8, 0, 0, 0, 0], [8, 0, 0, 0, 0, 0, 8], [8, 0, 0, 0, 0, 0, 8], [8, 0, 0, 0, 0, 0, 8], [0, 0, 0, 0, 0, 0, 8], [8, 0, 0, 0, 0, 0, 8], [8, 8, 8, 8, 8, 0, 8]], [[0, 8, 8, 8, 8, 8, 8], [8, 0, 0, 0, 0, 0, 8], [8, 0, 0, 0, 0, 0, 8], [8, 0, 0, 0, 0, 0, 8], [8, 0, 0, 0, 0, 0, 8], [8, 0, 0, 0, 0, 0, 8], [8, 0, 0, 0, 0, 0, 8], [8, 0, 0, 0, 0, 0, 8], [8, 8, 8, 8, 8, 0, 8]], [[8, 8, 8, 8, 8, 8, 8], [8, 0, 0, 0, 0, 0, 8], [8, 0, 0, 0, 0, 0, 8], [8, 0, 0, 0, 0, 0, 8], [8, 0, 0, 0, 0, 0, 8], [8, 0, 0, 0, 0, 0, 8], [8, 0, 0, 0, 0, 0, 8], [8, 0, 0, 0, 0, 0, 8], [8, 8, 8, 8, 8, 8, 8]], [[8, 8, 8, 8, 8, 8, 8], [8, 0, 0, 0, 0, 0, 8], [8, 0, 0, 0, 0, 0, 8], [8, 0, 0, 0, 0, 0, 8], [8, 0, 0, 0, 0, 0, 8], [8, 0, 0, 0, 0, 0, 8], [8, 0, 0, 0, 0, 0, 8], [8, 0, 0, 0, 0, 0, 8], [8, 8, 8, 8, 8, 8, 8]], [[8, 8, 8, 8, 8, 8, 8], [8, 0, 0, 0, 0, 0, 8], [8, 0, 0, 0, 0, 0, 8], [8, 0, 0, 0, 0, 0, 8], [8, 0, 0, 0, 0, 0, 8], [8, 0, 0, 0, 0, 0, 8], [8, 0, 0, 0, 0, 0, 8], [8, 0, 0, 0, 0, 0, 8], [8, 8, 8, 8, 8, 8, 8]], [[8, 8, 8, 8, 8, 8, 8], [8, 0, 0, 0, 0, 0, 8], [8, 0, 0, 0, 0, 0, 8], [8, 0, 0, 0, 0, 0, 8], [8, 0, 0, 0, 0, 0, 8], [8, 0, 0, 0, 0, 0, 8], [8, 0, 0, 0, 0, 0, 8], [8, 0, 0, 0, 0, 0, 8], [8, 8, 8, 8, 8, 8, 8]], [[8, 8, 8, 8, 8, 8, 8], [8, 0, 0, 0, 0, 0, 8], [8, 0, 0, 0, 0, 0, 8], [8, 0, 0, 0, 0, 0, 8], [8, 0, 0, 0, 0, 0, 8], [8, 0, 0, 0, 0, 0, 8], [8, 0, 0, 0, 0, 0, 8], [8, 0, 0, 0, 0, 0, 8], [8, 8, 8, 8, 8, 8, 8]], [[8, 8, 8, 8, 8, 8, 8], [8, 0, 0, 0, 0, 0, 8], [8, 0, 0, 0, 0, 0, 8], [8, 0, 0, 0, 0, 0, 8], [8, 0, 0, 0, 0, 0, 8], [8, 0, 0, 0, 0, 0, 8], [8, 0, 0, 0, 0, 0, 8], [8, 0, 0, 0, 0, 0, 8], [8, 8, 8, 8, 8, 8, 8]], [[8, 8, 8, 8, 8, 8, 8], [8, 0, 0, 0, 0, 0, 8], [8, 0, 0, 0, 0, 0, 8], [8, 0, 0, 0, 0, 0, 8], [8, 0, 0, 0, 0, 0, 8], [8, 0, 0, 0, 0, 0, 8], [8, 0, 0, 0, 0, 0, 8], [8, 0, 0, 0, 0, 0, 8], [8, 8, 8, 8, 8, 8, 8]], [[8, 8, 8, 8, 8, 8, 8], [8, 0, 0, 0, 0, 0, 8], [8, 0, 0, 0, 0, 0, 8], [8, 0, 0, 0, 0, 0, 8], [8, 0, 0, 0, 0, 0, 8], [8, 0, 0, 0, 0, 0, 8], [8, 0, 0, 0, 0, 0, 8], [8, 0, 0, 0, 0, 0, 8], [8, 8, 8, 8, 8, 8, 8]], [[8, 8, 8, 8, 8, 8, 8], [8, 0, 0, 0, 0, 0, 8], [8, 0, 0, 0, 0, 0, 8], [8, 0, 0, 0, 0, 0, 8], [8, 0, 0, 0, 0, 0, 8], [8, 0, 0, 0, 0, 0, 8], [8, 0, 0, 0, 0, 0, 8], [8, 0, 0, 0, 0, 0, 8], [8, 8, 8, 8, 8, 8, 8]], [[8, 8, 8, 8, 8, 8, 8], [8, 0, 0, 0, 0, 0, 8], [8, 0, 0, 0, 0, 0, 8], [8, 0, 0, 0, 0, 0, 8], [8, 0, 0, 0, 0, 0, 8], [8, 0, 0, 0, 0, 0, 8], [8, 0, 0, 0, 0, 0, 8], [8, 0, 0, 0, 0, 0, 8], [8, 8, 8, 8, 8, 8, 8]], [[8, 8, 8, 8, 8, 8, 8], [8, 0, 0, 0, 0, 0, 8], [8, 0, 0, 0, 0, 0, 8], [8, 0, 0, 0, 0, 0, 8], [8, 0, 0, 0, 0, 0, 8], [8, 0, 0, 0, 0, 0, 8], [8, 0, 0, 0, 0, 0, 8], [8, 0, 0, 0, 0, 0, 8], [8, 8, 8, 8, 8, 8, 8]], [[8, 8, 8, 8, 8, 8, 8], [8, 0, 0, 0, 0, 0, 8], [8, 0, 0, 0, 0, 0, 8], [8, 0, 0, 0, 0, 0, 8], [8, 0, 0, 0, 0, 0, 8], [8, 0, 0, 0, 0, 0, 8], [8, 0, 0, 0, 0, 0, 8], [8, 0, 0, 0, 0, 0, 8], [8, 8, 8, 8, 8, 8, 8]], [[8, 8, 8, 8, 8, 8, 8], [8, 0, 0, 0, 0, 0, 8], [8, 0, 0, 0, 0, 0, 8], [8, 0, 0, 0, 0, 0, 8], [8, 0, 0, 0, 0, 0, 8], [8, 0, 0, 0, 0, 0, 8], [8, 0, 0, 0, 0, 0, 8], [8, 0, 0, 0, 0, 0, 8], [8, 8, 8, 8, 8, 8, 8]], [[8, 8, 8, 8, 8, 8, 8], [8, 0, 0, 0, 0, 0, 8], [8, 0, 0, 0, 0, 0, 8], [8, 0, 0, 0, 0, 0, 8], [8, 0, 0, 0, 0, 0, 8], [8, 0, 0, 0, 0, 0, 8], [8, 0, 0, 0, 0, 0, 8], [8, 0, 0, 0, 0, 0, 8], [8, 8, 8, 8, 8, 8, 8]], [[8, 8, 8, 8, 8, 8, 8], [8, 0, 0, 0, 0, 0, 8], [8, 0, 0, 0, 0, 0, 8], [8, 0, 0, 0, 0, 0, 8], [8, 0, 0, 0, 0, 0, 8], [8, 0, 0, 0, 0, 0, 8], [8, 0, 0, 0, 0, 0, 8], [8, 0, 0, 0, 0, 0, 8], [8, 8, 8, 8, 8, 8, 8]], [[8, 8, 8, 8, 8, 8, 8], [8, 0, 0, 0, 0, 0, 8], [8, 0, 0, 0, 0, 0, 8], [8, 0, 0, 0, 0, 0, 8], [8, 0, 0, 0, 0, 0, 8], [8, 0, 0, 0, 0, 0, 8], [8, 0, 0, 0, 0, 0, 8], [8, 0, 0, 0, 0, 0, 8], [8, 8, 8, 8, 8, 8, 8]], [[8, 8, 8, 8, 8, 8, 8], [8, 0, 0, 0, 0, 0, 8], [8, 0, 0, 0, 0, 0, 8], [8, 0, 0, 0, 0, 0, 8], [8, 0, 0, 0, 0, 0, 8], [8, 0, 0, 0, 0, 0, 8], [8, 0, 0, 0, 0, 0, 8], [8, 0, 0, 0, 0, 0, 8], [8, 8, 8, 8, 8, 8, 8]], [[8, 8, 8, 8, 8, 8, 8], [8, 0, 0, 0, 0, 0, 8], [8, 0, 0, 0, 0, 0, 8], [8, 0, 0, 0, 0, 0, 8], [8, 0, 0, 0, 0, 0, 8], [8, 0, 0, 0, 0, 0, 8], [8, 0, 0, 0, 0, 0, 8], [8, 0, 0, 0, 0, 0, 8], [8, 8, 8, 8, 8, 8, 8]], [[8, 8, 8, 8, 8, 8, 8], [8, 0, 0, 0, 0, 0, 8], [8, 0, 0, 0, 0, 0, 8], [8, 0, 0, 0, 0, 0, 8], [8, 0, 0, 0, 0, 0, 8], [8, 0, 0, 0, 0, 0, 8], [8, 0, 0, 0, 0, 0, 8], [8, 0, 0, 0, 0, 0, 8], [8, 8, 8, 8, 8, 8, 8]], [[8, 8, 8, 8, 8, 8, 8], [8, 0, 0, 0, 0, 0, 8], [8, 0, 0, 0, 0, 0, 8], [8, 0, 0, 0, 0, 0, 8], [8, 0, 0, 0, 0, 0, 8], [8, 0, 0, 0, 0, 0, 8], [8, 0, 0, 0, 0, 0, 8], [8, 0, 0, 0, 0, 0, 8], [8, 8, 8, 8, 8, 8, 8]], [[8, 8, 8, 8, 8, 8, 8], [8, 0, 0, 0, 0, 0, 8], [8, 0, 0, 0, 0, 0, 8], [8, 0, 0, 0, 0, 0, 8], [8, 0, 0, 0, 0, 0, 8], [8, 0, 0, 0, 0, 0, 8], [8, 0, 0, 0, 0, 0, 8], [8, 0, 0, 0, 0, 0, 8], [8, 8, 8, 8, 8, 8, 8]], [[8, 8, 8, 8, 8, 8, 8], [8, 0, 0, 0, 0, 0, 8], [8, 0, 0, 0, 0, 0, 8], [8, 0, 0, 0, 0, 0, 8], [8, 0, 0, 0, 0, 0, 8], [8, 0, 0, 0, 0, 0, 8], [8, 0, 0, 0, 0, 0, 8], [8, 0, 0, 0, 0, 0, 8], [8, 8, 8, 8, 8, 8, 8]], [[8, 8, 8, 8, 8, 8, 8], [8, 0, 0, 0, 0, 0, 8], [8, 0, 0, 0, 0, 0, 8], [8, 0, 0, 0, 0, 0, 8], [8, 0, 0, 0, 0, 0, 8], [8, 0, 0, 0, 0, 0, 8], [8, 0, 0, 0, 0, 0, 8], [8, 0, 0, 0, 0, 0, 8], [8, 8, 8, 8, 8, 8, 8]], [[8, 8, 8, 8, 8, 8, 8], [8, 0, 0, 0, 0, 0, 8], [8, 0, 0, 0, 0, 0, 8], [8, 0, 0, 0, 0, 0, 8], [8, 0, 0, 0, 0, 0, 8], [8, 0, 0, 0, 0, 0, 8], [8, 0, 0, 0, 0, 0, 8], [8, 0, 0, 0, 0, 0, 8], [8, 8, 8, 8, 8, 8, 8]], [[8, 8, 8, 8, 8, 8, 8], [8, 0, 0, 0, 0, 0, 8], [8, 0, 0, 0, 0, 0, 8], [8, 0, 0, 0, 0, 0, 8], [8, 0, 0, 0, 0, 0, 8], [8, 0, 0, 0, 0, 0, 8], [8, 0, 0, 0, 0, 0, 8], [8, 0, 0, 0, 0, 0, 8], [8, 8, 8, 8, 8, 8, 8]], [[8, 8, 8, 8, 8, 8, 8], [8, 0, 0, 0, 0, 0, 8], [8, 0, 0, 0, 0, 0, 8], [8, 0, 0, 0, 0, 0, 8], [8, 0, 0, 0, 0, 0, 8], [8, 0, 0, 0, 0, 0, 8], [8, 0, 0, 0, 0, 0, 8], [8, 0, 0, 0, 0, 0, 8], [8, 8, 8, 8, 8, 8, 8]], [[8, 8, 8, 8, 8, 8, 8], [8, 0, 0, 0, 0, 0, 8], [8, 0, 0, 0, 0, 0, 8], [8, 0, 0, 0, 0, 0, 8], [8, 0, 0, 0, 0, 0, 8], [8, 0, 0, 0, 0, 0, 8], [8, 0, 0, 0, 0, 0, 8], [8, 0, 0, 0, 0, 0, 8], [8, 8, 8, 8, 8, 8, 8]], [[8, 8, 8, 8, 8, 8, 8], [8, 0, 0, 0, 0, 0, 8], [8, 0, 0, 0, 0, 0, 8], [8, 0, 0, 0, 0, 0, 8], [8, 0, 0, 0, 0, 0, 8], [8, 0, 0, 0, 0, 0, 8], [8, 0, 0, 0, 0, 0, 8], [8, 0, 0, 0, 0, 0, 8], [8, 8, 8, 8, 8, 8, 8]]], "target": [[8, 8, 8, 8, 8, 8, 8], [8, 0, 0, 0, 0, 0, 8], [8, 0, 0, 0, 0, 0, 8], [8, 0, 0, 0, 0, 0, 8], [8, 0, 0, 0, 0, 0, 8], [8, 0, 0, 0, 0, 0, 8], [8, 0, 0, 0, 0, 0, 8], [8, 0, 0, 0, 0, 0, 8], [8, 8, 8, 8, 8, 8, 8]]}}